package com.tencent.mm.sdk.b;

import com.tencent.mm.a.a;

public final class d
{
  private final a r;
  private c<String, String> s;

  // ERROR //
  public final String b(String paramString)
  {
    // Byte code:
    //   0: aload_1
    //   1: ldc 15
    //   3: invokevirtual 21	java/lang/String:startsWith	(Ljava/lang/String;)Z
    //   6: ifeq +169 -> 175
    //   9: aload_0
    //   10: getfield 23	com/tencent/mm/sdk/b/d:s	Lcom/tencent/mm/sdk/b/c;
    //   13: aload_1
    //   14: invokevirtual 29	com/tencent/mm/sdk/b/c:a	(Ljava/lang/Object;)Z
    //   17: ifeq +15 -> 32
    //   20: aload_0
    //   21: getfield 23	com/tencent/mm/sdk/b/d:s	Lcom/tencent/mm/sdk/b/c;
    //   24: aload_1
    //   25: invokevirtual 33	com/tencent/mm/sdk/b/c:get	(Ljava/lang/Object;)Ljava/lang/Object;
    //   28: checkcast 17	java/lang/String
    //   31: areturn
    //   32: aload_1
    //   33: iconst_1
    //   34: invokevirtual 37	java/lang/String:substring	(I)Ljava/lang/String;
    //   37: astore_3
    //   38: aload_3
    //   39: ldc 39
    //   41: invokevirtual 43	java/lang/String:split	(Ljava/lang/String;)[Ljava/lang/String;
    //   44: astore 5
    //   46: aload 5
    //   48: arraylength
    //   49: iconst_1
    //   50: if_icmple +137 -> 187
    //   53: aload 5
    //   55: iconst_0
    //   56: aaload
    //   57: astore 6
    //   59: aload 5
    //   61: iconst_0
    //   62: aaload
    //   63: invokestatic 49	java/lang/Integer:valueOf	(Ljava/lang/String;)Ljava/lang/Integer;
    //   66: invokevirtual 53	java/lang/Integer:intValue	()I
    //   69: istore 7
    //   71: aload_3
    //   72: iconst_1
    //   73: aload 6
    //   75: invokevirtual 56	java/lang/String:length	()I
    //   78: iadd
    //   79: iload 7
    //   81: iconst_1
    //   82: aload 6
    //   84: invokevirtual 56	java/lang/String:length	()I
    //   87: iadd
    //   88: iadd
    //   89: invokevirtual 59	java/lang/String:substring	(II)Ljava/lang/String;
    //   92: astore 8
    //   94: aload_3
    //   95: iload 7
    //   97: iconst_1
    //   98: aload 6
    //   100: invokevirtual 56	java/lang/String:length	()I
    //   103: iadd
    //   104: iadd
    //   105: invokevirtual 37	java/lang/String:substring	(I)Ljava/lang/String;
    //   108: astore 9
    //   110: new 61	java/lang/StringBuilder
    //   113: dup
    //   114: invokespecial 65	java/lang/StringBuilder:<init>	()V
    //   117: aload_0
    //   118: getfield 67	com/tencent/mm/sdk/b/d:r	Lcom/tencent/mm/a/a;
    //   121: aload 8
    //   123: invokevirtual 71	com/tencent/mm/a/a:a	(Ljava/lang/String;)Ljava/lang/String;
    //   126: invokevirtual 75	java/lang/StringBuilder:append	(Ljava/lang/String;)Ljava/lang/StringBuilder;
    //   129: aload 9
    //   131: invokevirtual 75	java/lang/StringBuilder:append	(Ljava/lang/String;)Ljava/lang/StringBuilder;
    //   134: invokevirtual 79	java/lang/StringBuilder:toString	()Ljava/lang/String;
    //   137: astore 10
    //   139: aload_0
    //   140: getfield 23	com/tencent/mm/sdk/b/d:s	Lcom/tencent/mm/sdk/b/c;
    //   143: aload_1
    //   144: aload 10
    //   146: invokevirtual 83	com/tencent/mm/sdk/b/c:put	(Ljava/lang/Object;Ljava/lang/Object;)Ljava/lang/Object;
    //   149: pop
    //   150: aload 10
    //   152: areturn
    //   153: astore_2
    //   154: aload_2
    //   155: invokevirtual 86	java/lang/Exception:printStackTrace	()V
    //   158: new 61	java/lang/StringBuilder
    //   161: dup
    //   162: ldc 88
    //   164: invokespecial 91	java/lang/StringBuilder:<init>	(Ljava/lang/String;)V
    //   167: aload_1
    //   168: invokevirtual 75	java/lang/StringBuilder:append	(Ljava/lang/String;)Ljava/lang/StringBuilder;
    //   171: invokevirtual 79	java/lang/StringBuilder:toString	()Ljava/lang/String;
    //   174: astore_1
    //   175: aload_1
    //   176: areturn
    //   177: astore 4
    //   179: aload_3
    //   180: astore_1
    //   181: aload 4
    //   183: astore_2
    //   184: goto -30 -> 154
    //   187: aload_3
    //   188: astore_1
    //   189: goto -14 -> 175
    //
    // Exception table:
    //   from	to	target	type
    //   0	32	153	java/lang/Exception
    //   32	38	153	java/lang/Exception
    //   38	150	177	java/lang/Exception
  }
}

/* Location:           /Users/zhangxun-xy/Downloads/qingting2/classes_dex2jar.jar
 * Qualified Name:     com.tencent.mm.sdk.b.d
 * JD-Core Version:    0.6.2
 */