package com.taobao.munion.base.caches;

public class n
{
  public static final String a = "mmusdk_cache";
  public static final String b = "content";
  public static final String c = "meta";
  public static final String d = "name";
  public static final String e = "(?<=meta name=\"mmusdk_cache\" content=\").*?(?=\")";

  // ERROR //
  public java.util.List<b.a> a(String paramString)
  {
    // Byte code:
    //   0: ldc 20
    //   2: invokestatic 33	java/util/regex/Pattern:compile	(Ljava/lang/String;)Ljava/util/regex/Pattern;
    //   5: aload_1
    //   6: invokevirtual 37	java/util/regex/Pattern:matcher	(Ljava/lang/CharSequence;)Ljava/util/regex/Matcher;
    //   9: astore 5
    //   11: aconst_null
    //   12: astore_3
    //   13: aload 5
    //   15: invokevirtual 43	java/util/regex/Matcher:find	()Z
    //   18: ifeq +62 -> 80
    //   21: aload_3
    //   22: ifnonnull +77 -> 99
    //   25: new 45	java/util/ArrayList
    //   28: dup
    //   29: invokespecial 46	java/util/ArrayList:<init>	()V
    //   32: astore 6
    //   34: new 48	com/taobao/munion/base/caches/b$a
    //   37: dup
    //   38: invokespecial 49	com/taobao/munion/base/caches/b$a:<init>	()V
    //   41: astore 7
    //   43: aload 7
    //   45: aload 5
    //   47: invokevirtual 53	java/util/regex/Matcher:group	()Ljava/lang/String;
    //   50: invokevirtual 56	com/taobao/munion/base/caches/b$a:a	(Ljava/lang/String;)V
    //   53: aload 6
    //   55: aload 7
    //   57: invokeinterface 62 2 0
    //   62: pop
    //   63: aload 6
    //   65: astore_3
    //   66: goto -53 -> 13
    //   69: astore_2
    //   70: aconst_null
    //   71: astore_3
    //   72: aload_2
    //   73: astore 4
    //   75: aload 4
    //   77: invokevirtual 65	java/lang/Exception:printStackTrace	()V
    //   80: aload_3
    //   81: areturn
    //   82: astore 8
    //   84: aload 6
    //   86: astore_3
    //   87: aload 8
    //   89: astore 4
    //   91: goto -16 -> 75
    //   94: astore 4
    //   96: goto -21 -> 75
    //   99: aload_3
    //   100: astore 6
    //   102: goto -68 -> 34
    //
    // Exception table:
    //   from	to	target	type
    //   0	11	69	java/lang/Exception
    //   34	63	82	java/lang/Exception
    //   13	21	94	java/lang/Exception
    //   25	34	94	java/lang/Exception
  }
}

/* Location:           /Users/zhangxun-xy/Downloads/qingting2/classes_dex2jar.jar
 * Qualified Name:     com.taobao.munion.base.caches.n
 * JD-Core Version:    0.6.2
 */