package weibo4android.org.json;

public class Test
{
  // ERROR //
  public static void main(String[] paramArrayOfString)
  {
    // Byte code:
    //   0: new 14	weibo4android/org/json/Test$1Obj
    //   3: dup
    //   4: ldc 16
    //   6: ldc2_w 17
    //   9: iconst_1
    //   10: invokespecial 21	weibo4android/org/json/Test$1Obj:<init>	(Ljava/lang/String;DZ)V
    //   13: astore_1
    //   14: ldc 23
    //   16: invokestatic 29	weibo4android/org/json/XML:toJSONObject	(Ljava/lang/String;)Lweibo4android/org/json/JSONObject;
    //   19: astore_3
    //   20: getstatic 35	java/lang/System:out	Ljava/io/PrintStream;
    //   23: aload_3
    //   24: invokevirtual 41	weibo4android/org/json/JSONObject:toString	()Ljava/lang/String;
    //   27: invokevirtual 47	java/io/PrintStream:println	(Ljava/lang/String;)V
    //   30: new 37	weibo4android/org/json/JSONObject
    //   33: dup
    //   34: ldc 49
    //   36: invokespecial 51	weibo4android/org/json/JSONObject:<init>	(Ljava/lang/String;)V
    //   39: astore 4
    //   41: getstatic 35	java/lang/System:out	Ljava/io/PrintStream;
    //   44: aload 4
    //   46: iconst_4
    //   47: invokevirtual 54	weibo4android/org/json/JSONObject:toString	(I)Ljava/lang/String;
    //   50: invokevirtual 47	java/io/PrintStream:println	(Ljava/lang/String;)V
    //   53: getstatic 35	java/lang/System:out	Ljava/io/PrintStream;
    //   56: aload 4
    //   58: invokestatic 57	weibo4android/org/json/XML:toString	(Ljava/lang/Object;)Ljava/lang/String;
    //   61: invokevirtual 47	java/io/PrintStream:println	(Ljava/lang/String;)V
    //   64: ldc 59
    //   66: invokestatic 29	weibo4android/org/json/XML:toJSONObject	(Ljava/lang/String;)Lweibo4android/org/json/JSONObject;
    //   69: astore 5
    //   71: getstatic 35	java/lang/System:out	Ljava/io/PrintStream;
    //   74: aload 5
    //   76: iconst_4
    //   77: invokevirtual 54	weibo4android/org/json/JSONObject:toString	(I)Ljava/lang/String;
    //   80: invokevirtual 47	java/io/PrintStream:println	(Ljava/lang/String;)V
    //   83: getstatic 35	java/lang/System:out	Ljava/io/PrintStream;
    //   86: invokevirtual 61	java/io/PrintStream:println	()V
    //   89: ldc 59
    //   91: invokestatic 64	weibo4android/org/json/JSONML:toJSONObject	(Ljava/lang/String;)Lweibo4android/org/json/JSONObject;
    //   94: astore 6
    //   96: getstatic 35	java/lang/System:out	Ljava/io/PrintStream;
    //   99: aload 6
    //   101: invokevirtual 41	weibo4android/org/json/JSONObject:toString	()Ljava/lang/String;
    //   104: invokevirtual 47	java/io/PrintStream:println	(Ljava/lang/String;)V
    //   107: getstatic 35	java/lang/System:out	Ljava/io/PrintStream;
    //   110: aload 6
    //   112: invokestatic 67	weibo4android/org/json/JSONML:toString	(Lweibo4android/org/json/JSONObject;)Ljava/lang/String;
    //   115: invokevirtual 47	java/io/PrintStream:println	(Ljava/lang/String;)V
    //   118: getstatic 35	java/lang/System:out	Ljava/io/PrintStream;
    //   121: invokevirtual 61	java/io/PrintStream:println	()V
    //   124: ldc 59
    //   126: invokestatic 71	weibo4android/org/json/JSONML:toJSONArray	(Ljava/lang/String;)Lweibo4android/org/json/JSONArray;
    //   129: astore 7
    //   131: getstatic 35	java/lang/System:out	Ljava/io/PrintStream;
    //   134: aload 7
    //   136: iconst_4
    //   137: invokevirtual 74	weibo4android/org/json/JSONArray:toString	(I)Ljava/lang/String;
    //   140: invokevirtual 47	java/io/PrintStream:println	(Ljava/lang/String;)V
    //   143: getstatic 35	java/lang/System:out	Ljava/io/PrintStream;
    //   146: aload 7
    //   148: invokestatic 77	weibo4android/org/json/JSONML:toString	(Lweibo4android/org/json/JSONArray;)Ljava/lang/String;
    //   151: invokevirtual 47	java/io/PrintStream:println	(Ljava/lang/String;)V
    //   154: getstatic 35	java/lang/System:out	Ljava/io/PrintStream;
    //   157: invokevirtual 61	java/io/PrintStream:println	()V
    //   160: ldc 79
    //   162: invokestatic 64	weibo4android/org/json/JSONML:toJSONObject	(Ljava/lang/String;)Lweibo4android/org/json/JSONObject;
    //   165: astore 8
    //   167: getstatic 35	java/lang/System:out	Ljava/io/PrintStream;
    //   170: aload 8
    //   172: iconst_4
    //   173: invokevirtual 54	weibo4android/org/json/JSONObject:toString	(I)Ljava/lang/String;
    //   176: invokevirtual 47	java/io/PrintStream:println	(Ljava/lang/String;)V
    //   179: getstatic 35	java/lang/System:out	Ljava/io/PrintStream;
    //   182: aload 8
    //   184: invokestatic 67	weibo4android/org/json/JSONML:toString	(Lweibo4android/org/json/JSONObject;)Ljava/lang/String;
    //   187: invokevirtual 47	java/io/PrintStream:println	(Ljava/lang/String;)V
    //   190: getstatic 35	java/lang/System:out	Ljava/io/PrintStream;
    //   193: invokevirtual 61	java/io/PrintStream:println	()V
    //   196: ldc 79
    //   198: invokestatic 71	weibo4android/org/json/JSONML:toJSONArray	(Ljava/lang/String;)Lweibo4android/org/json/JSONArray;
    //   201: astore 9
    //   203: getstatic 35	java/lang/System:out	Ljava/io/PrintStream;
    //   206: aload 9
    //   208: iconst_4
    //   209: invokevirtual 74	weibo4android/org/json/JSONArray:toString	(I)Ljava/lang/String;
    //   212: invokevirtual 47	java/io/PrintStream:println	(Ljava/lang/String;)V
    //   215: getstatic 35	java/lang/System:out	Ljava/io/PrintStream;
    //   218: aload 9
    //   220: invokestatic 77	weibo4android/org/json/JSONML:toString	(Lweibo4android/org/json/JSONArray;)Ljava/lang/String;
    //   223: invokevirtual 47	java/io/PrintStream:println	(Ljava/lang/String;)V
    //   226: getstatic 35	java/lang/System:out	Ljava/io/PrintStream;
    //   229: invokevirtual 61	java/io/PrintStream:println	()V
    //   232: ldc 81
    //   234: invokestatic 29	weibo4android/org/json/XML:toJSONObject	(Ljava/lang/String;)Lweibo4android/org/json/JSONObject;
    //   237: astore 10
    //   239: getstatic 35	java/lang/System:out	Ljava/io/PrintStream;
    //   242: aload 10
    //   244: iconst_4
    //   245: invokevirtual 54	weibo4android/org/json/JSONObject:toString	(I)Ljava/lang/String;
    //   248: invokevirtual 47	java/io/PrintStream:println	(Ljava/lang/String;)V
    //   251: new 37	weibo4android/org/json/JSONObject
    //   254: dup
    //   255: aload_1
    //   256: invokespecial 84	weibo4android/org/json/JSONObject:<init>	(Ljava/lang/Object;)V
    //   259: astore 11
    //   261: getstatic 35	java/lang/System:out	Ljava/io/PrintStream;
    //   264: aload 11
    //   266: invokevirtual 41	weibo4android/org/json/JSONObject:toString	()Ljava/lang/String;
    //   269: invokevirtual 47	java/io/PrintStream:println	(Ljava/lang/String;)V
    //   272: new 37	weibo4android/org/json/JSONObject
    //   275: dup
    //   276: ldc 86
    //   278: invokespecial 51	weibo4android/org/json/JSONObject:<init>	(Ljava/lang/String;)V
    //   281: astore 12
    //   283: getstatic 35	java/lang/System:out	Ljava/io/PrintStream;
    //   286: aload 12
    //   288: iconst_2
    //   289: invokevirtual 54	weibo4android/org/json/JSONObject:toString	(I)Ljava/lang/String;
    //   292: invokevirtual 47	java/io/PrintStream:println	(Ljava/lang/String;)V
    //   295: new 88	weibo4android/org/json/JSONStringer
    //   298: dup
    //   299: invokespecial 89	weibo4android/org/json/JSONStringer:<init>	()V
    //   302: invokevirtual 93	weibo4android/org/json/JSONStringer:object	()Lweibo4android/org/json/JSONWriter;
    //   305: ldc 95
    //   307: invokevirtual 101	weibo4android/org/json/JSONWriter:key	(Ljava/lang/String;)Lweibo4android/org/json/JSONWriter;
    //   310: ldc 103
    //   312: invokevirtual 107	weibo4android/org/json/JSONWriter:value	(Ljava/lang/Object;)Lweibo4android/org/json/JSONWriter;
    //   315: ldc 109
    //   317: invokevirtual 101	weibo4android/org/json/JSONWriter:key	(Ljava/lang/String;)Lweibo4android/org/json/JSONWriter;
    //   320: ldc 111
    //   322: invokevirtual 107	weibo4android/org/json/JSONWriter:value	(Ljava/lang/Object;)Lweibo4android/org/json/JSONWriter;
    //   325: ldc 113
    //   327: invokevirtual 101	weibo4android/org/json/JSONWriter:key	(Ljava/lang/String;)Lweibo4android/org/json/JSONWriter;
    //   330: ldc 115
    //   332: invokevirtual 107	weibo4android/org/json/JSONWriter:value	(Ljava/lang/Object;)Lweibo4android/org/json/JSONWriter;
    //   335: ldc 117
    //   337: invokevirtual 101	weibo4android/org/json/JSONWriter:key	(Ljava/lang/String;)Lweibo4android/org/json/JSONWriter;
    //   340: invokevirtual 120	weibo4android/org/json/JSONWriter:array	()Lweibo4android/org/json/JSONWriter;
    //   343: invokevirtual 121	weibo4android/org/json/JSONWriter:object	()Lweibo4android/org/json/JSONWriter;
    //   346: ldc 123
    //   348: invokevirtual 101	weibo4android/org/json/JSONWriter:key	(Ljava/lang/String;)Lweibo4android/org/json/JSONWriter;
    //   351: ldc 125
    //   353: invokevirtual 107	weibo4android/org/json/JSONWriter:value	(Ljava/lang/Object;)Lweibo4android/org/json/JSONWriter;
    //   356: invokevirtual 128	weibo4android/org/json/JSONWriter:endObject	()Lweibo4android/org/json/JSONWriter;
    //   359: invokevirtual 131	weibo4android/org/json/JSONWriter:endArray	()Lweibo4android/org/json/JSONWriter;
    //   362: ldc 133
    //   364: invokevirtual 101	weibo4android/org/json/JSONWriter:key	(Ljava/lang/String;)Lweibo4android/org/json/JSONWriter;
    //   367: aload_1
    //   368: invokestatic 137	weibo4android/org/json/JSONObject:getNames	(Ljava/lang/Object;)[Ljava/lang/String;
    //   371: invokevirtual 107	weibo4android/org/json/JSONWriter:value	(Ljava/lang/Object;)Lweibo4android/org/json/JSONWriter;
    //   374: invokevirtual 128	weibo4android/org/json/JSONWriter:endObject	()Lweibo4android/org/json/JSONWriter;
    //   377: invokevirtual 138	java/lang/Object:toString	()Ljava/lang/String;
    //   380: astore 13
    //   382: getstatic 35	java/lang/System:out	Ljava/io/PrintStream;
    //   385: aload 13
    //   387: invokevirtual 47	java/io/PrintStream:println	(Ljava/lang/String;)V
    //   390: getstatic 35	java/lang/System:out	Ljava/io/PrintStream;
    //   393: new 88	weibo4android/org/json/JSONStringer
    //   396: dup
    //   397: invokespecial 89	weibo4android/org/json/JSONStringer:<init>	()V
    //   400: invokevirtual 93	weibo4android/org/json/JSONStringer:object	()Lweibo4android/org/json/JSONWriter;
    //   403: ldc 140
    //   405: invokevirtual 101	weibo4android/org/json/JSONWriter:key	(Ljava/lang/String;)Lweibo4android/org/json/JSONWriter;
    //   408: invokevirtual 120	weibo4android/org/json/JSONWriter:array	()Lweibo4android/org/json/JSONWriter;
    //   411: invokevirtual 120	weibo4android/org/json/JSONWriter:array	()Lweibo4android/org/json/JSONWriter;
    //   414: invokevirtual 120	weibo4android/org/json/JSONWriter:array	()Lweibo4android/org/json/JSONWriter;
    //   417: ldc 142
    //   419: invokevirtual 107	weibo4android/org/json/JSONWriter:value	(Ljava/lang/Object;)Lweibo4android/org/json/JSONWriter;
    //   422: invokevirtual 131	weibo4android/org/json/JSONWriter:endArray	()Lweibo4android/org/json/JSONWriter;
    //   425: invokevirtual 131	weibo4android/org/json/JSONWriter:endArray	()Lweibo4android/org/json/JSONWriter;
    //   428: invokevirtual 131	weibo4android/org/json/JSONWriter:endArray	()Lweibo4android/org/json/JSONWriter;
    //   431: invokevirtual 128	weibo4android/org/json/JSONWriter:endObject	()Lweibo4android/org/json/JSONWriter;
    //   434: invokevirtual 138	java/lang/Object:toString	()Ljava/lang/String;
    //   437: invokevirtual 47	java/io/PrintStream:println	(Ljava/lang/String;)V
    //   440: new 88	weibo4android/org/json/JSONStringer
    //   443: dup
    //   444: invokespecial 89	weibo4android/org/json/JSONStringer:<init>	()V
    //   447: astore 14
    //   449: aload 14
    //   451: invokevirtual 143	weibo4android/org/json/JSONStringer:array	()Lweibo4android/org/json/JSONWriter;
    //   454: pop
    //   455: aload 14
    //   457: lconst_1
    //   458: invokevirtual 146	weibo4android/org/json/JSONStringer:value	(J)Lweibo4android/org/json/JSONWriter;
    //   461: pop
    //   462: aload 14
    //   464: invokevirtual 143	weibo4android/org/json/JSONStringer:array	()Lweibo4android/org/json/JSONWriter;
    //   467: pop
    //   468: aload 14
    //   470: aconst_null
    //   471: invokevirtual 147	weibo4android/org/json/JSONStringer:value	(Ljava/lang/Object;)Lweibo4android/org/json/JSONWriter;
    //   474: pop
    //   475: aload 14
    //   477: invokevirtual 143	weibo4android/org/json/JSONStringer:array	()Lweibo4android/org/json/JSONWriter;
    //   480: pop
    //   481: aload 14
    //   483: invokevirtual 93	weibo4android/org/json/JSONStringer:object	()Lweibo4android/org/json/JSONWriter;
    //   486: pop
    //   487: aload 14
    //   489: ldc 149
    //   491: invokevirtual 150	weibo4android/org/json/JSONStringer:key	(Ljava/lang/String;)Lweibo4android/org/json/JSONWriter;
    //   494: invokevirtual 120	weibo4android/org/json/JSONWriter:array	()Lweibo4android/org/json/JSONWriter;
    //   497: invokevirtual 131	weibo4android/org/json/JSONWriter:endArray	()Lweibo4android/org/json/JSONWriter;
    //   500: pop
    //   501: aload 14
    //   503: ldc 152
    //   505: invokevirtual 150	weibo4android/org/json/JSONStringer:key	(Ljava/lang/String;)Lweibo4android/org/json/JSONWriter;
    //   508: ldc2_w 153
    //   511: invokevirtual 155	weibo4android/org/json/JSONWriter:value	(J)Lweibo4android/org/json/JSONWriter;
    //   514: pop
    //   515: aload 14
    //   517: ldc 157
    //   519: invokevirtual 150	weibo4android/org/json/JSONStringer:key	(Ljava/lang/String;)Lweibo4android/org/json/JSONWriter;
    //   522: aconst_null
    //   523: invokevirtual 107	weibo4android/org/json/JSONWriter:value	(Ljava/lang/Object;)Lweibo4android/org/json/JSONWriter;
    //   526: pop
    //   527: aload 14
    //   529: ldc 159
    //   531: invokevirtual 150	weibo4android/org/json/JSONStringer:key	(Ljava/lang/String;)Lweibo4android/org/json/JSONWriter;
    //   534: iconst_0
    //   535: invokevirtual 162	weibo4android/org/json/JSONWriter:value	(Z)Lweibo4android/org/json/JSONWriter;
    //   538: pop
    //   539: aload 14
    //   541: ldc 164
    //   543: invokevirtual 150	weibo4android/org/json/JSONStringer:key	(Ljava/lang/String;)Lweibo4android/org/json/JSONWriter;
    //   546: iconst_1
    //   547: invokevirtual 162	weibo4android/org/json/JSONWriter:value	(Z)Lweibo4android/org/json/JSONWriter;
    //   550: pop
    //   551: aload 14
    //   553: ldc 166
    //   555: invokevirtual 150	weibo4android/org/json/JSONStringer:key	(Ljava/lang/String;)Lweibo4android/org/json/JSONWriter;
    //   558: ldc2_w 167
    //   561: invokevirtual 171	weibo4android/org/json/JSONWriter:value	(D)Lweibo4android/org/json/JSONWriter;
    //   564: pop
    //   565: aload 14
    //   567: ldc 173
    //   569: invokevirtual 150	weibo4android/org/json/JSONStringer:key	(Ljava/lang/String;)Lweibo4android/org/json/JSONWriter;
    //   572: ldc2_w 174
    //   575: invokevirtual 171	weibo4android/org/json/JSONWriter:value	(D)Lweibo4android/org/json/JSONWriter;
    //   578: pop
    //   579: aload 14
    //   581: ldc 177
    //   583: invokevirtual 150	weibo4android/org/json/JSONStringer:key	(Ljava/lang/String;)Lweibo4android/org/json/JSONWriter;
    //   586: invokevirtual 121	weibo4android/org/json/JSONWriter:object	()Lweibo4android/org/json/JSONWriter;
    //   589: invokevirtual 128	weibo4android/org/json/JSONWriter:endObject	()Lweibo4android/org/json/JSONWriter;
    //   592: pop
    //   593: aload 14
    //   595: ldc 179
    //   597: invokevirtual 150	weibo4android/org/json/JSONStringer:key	(Ljava/lang/String;)Lweibo4android/org/json/JSONWriter;
    //   600: pop
    //   601: aload 14
    //   603: ldc2_w 180
    //   606: invokevirtual 146	weibo4android/org/json/JSONStringer:value	(J)Lweibo4android/org/json/JSONWriter;
    //   609: pop
    //   610: aload 14
    //   612: invokevirtual 182	weibo4android/org/json/JSONStringer:endObject	()Lweibo4android/org/json/JSONWriter;
    //   615: pop
    //   616: aload 14
    //   618: ldc 184
    //   620: invokevirtual 147	weibo4android/org/json/JSONStringer:value	(Ljava/lang/Object;)Lweibo4android/org/json/JSONWriter;
    //   623: pop
    //   624: aload 14
    //   626: invokevirtual 185	weibo4android/org/json/JSONStringer:endArray	()Lweibo4android/org/json/JSONWriter;
    //   629: pop
    //   630: aload 14
    //   632: iconst_1
    //   633: invokevirtual 186	weibo4android/org/json/JSONStringer:value	(Z)Lweibo4android/org/json/JSONWriter;
    //   636: pop
    //   637: aload 14
    //   639: invokevirtual 185	weibo4android/org/json/JSONStringer:endArray	()Lweibo4android/org/json/JSONWriter;
    //   642: pop
    //   643: aload 14
    //   645: ldc2_w 187
    //   648: invokevirtual 189	weibo4android/org/json/JSONStringer:value	(D)Lweibo4android/org/json/JSONWriter;
    //   651: pop
    //   652: aload 14
    //   654: ldc2_w 190
    //   657: invokevirtual 189	weibo4android/org/json/JSONStringer:value	(D)Lweibo4android/org/json/JSONWriter;
    //   660: pop
    //   661: aload 14
    //   663: invokevirtual 93	weibo4android/org/json/JSONStringer:object	()Lweibo4android/org/json/JSONWriter;
    //   666: pop
    //   667: aload 14
    //   669: invokevirtual 182	weibo4android/org/json/JSONStringer:endObject	()Lweibo4android/org/json/JSONWriter;
    //   672: pop
    //   673: aload 14
    //   675: invokevirtual 93	weibo4android/org/json/JSONStringer:object	()Lweibo4android/org/json/JSONWriter;
    //   678: pop
    //   679: aload 14
    //   681: ldc 193
    //   683: invokevirtual 150	weibo4android/org/json/JSONStringer:key	(Ljava/lang/String;)Lweibo4android/org/json/JSONWriter;
    //   686: pop
    //   687: aload 14
    //   689: dconst_1
    //   690: invokevirtual 189	weibo4android/org/json/JSONStringer:value	(D)Lweibo4android/org/json/JSONWriter;
    //   693: pop
    //   694: aload 14
    //   696: invokevirtual 182	weibo4android/org/json/JSONStringer:endObject	()Lweibo4android/org/json/JSONWriter;
    //   699: pop
    //   700: aload 14
    //   702: aload_1
    //   703: invokevirtual 147	weibo4android/org/json/JSONStringer:value	(Ljava/lang/Object;)Lweibo4android/org/json/JSONWriter;
    //   706: pop
    //   707: aload 14
    //   709: invokevirtual 185	weibo4android/org/json/JSONStringer:endArray	()Lweibo4android/org/json/JSONWriter;
    //   712: pop
    //   713: getstatic 35	java/lang/System:out	Ljava/io/PrintStream;
    //   716: aload 14
    //   718: invokevirtual 194	weibo4android/org/json/JSONStringer:toString	()Ljava/lang/String;
    //   721: invokevirtual 47	java/io/PrintStream:println	(Ljava/lang/String;)V
    //   724: getstatic 35	java/lang/System:out	Ljava/io/PrintStream;
    //   727: new 73	weibo4android/org/json/JSONArray
    //   730: dup
    //   731: aload 14
    //   733: invokevirtual 194	weibo4android/org/json/JSONStringer:toString	()Ljava/lang/String;
    //   736: invokespecial 195	weibo4android/org/json/JSONArray:<init>	(Ljava/lang/String;)V
    //   739: iconst_4
    //   740: invokevirtual 74	weibo4android/org/json/JSONArray:toString	(I)Ljava/lang/String;
    //   743: invokevirtual 47	java/io/PrintStream:println	(Ljava/lang/String;)V
    //   746: new 73	weibo4android/org/json/JSONArray
    //   749: dup
    //   750: iconst_3
    //   751: newarray int
    //   753: dup
    //   754: iconst_0
    //   755: iconst_1
    //   756: iastore
    //   757: dup
    //   758: iconst_1
    //   759: iconst_2
    //   760: iastore
    //   761: dup
    //   762: iconst_2
    //   763: iconst_3
    //   764: iastore
    //   765: invokespecial 196	weibo4android/org/json/JSONArray:<init>	(Ljava/lang/Object;)V
    //   768: astore 46
    //   770: getstatic 35	java/lang/System:out	Ljava/io/PrintStream;
    //   773: aload 46
    //   775: invokevirtual 197	weibo4android/org/json/JSONArray:toString	()Ljava/lang/String;
    //   778: invokevirtual 47	java/io/PrintStream:println	(Ljava/lang/String;)V
    //   781: new 37	weibo4android/org/json/JSONObject
    //   784: dup
    //   785: aload_1
    //   786: iconst_3
    //   787: anewarray 199	java/lang/String
    //   790: dup
    //   791: iconst_0
    //   792: ldc 201
    //   794: aastore
    //   795: dup
    //   796: iconst_1
    //   797: ldc 203
    //   799: aastore
    //   800: dup
    //   801: iconst_2
    //   802: ldc 205
    //   804: aastore
    //   805: invokespecial 208	weibo4android/org/json/JSONObject:<init>	(Ljava/lang/Object;[Ljava/lang/String;)V
    //   808: astore 47
    //   810: aload 47
    //   812: ldc 210
    //   814: aload_1
    //   815: invokevirtual 214	weibo4android/org/json/JSONObject:put	(Ljava/lang/String;Ljava/lang/Object;)Lweibo4android/org/json/JSONObject;
    //   818: pop
    //   819: getstatic 35	java/lang/System:out	Ljava/io/PrintStream;
    //   822: aload 47
    //   824: iconst_4
    //   825: invokevirtual 54	weibo4android/org/json/JSONObject:toString	(I)Ljava/lang/String;
    //   828: invokevirtual 47	java/io/PrintStream:println	(Ljava/lang/String;)V
    //   831: new 37	weibo4android/org/json/JSONObject
    //   834: dup
    //   835: ldc 216
    //   837: invokespecial 51	weibo4android/org/json/JSONObject:<init>	(Ljava/lang/String;)V
    //   840: astore 49
    //   842: getstatic 35	java/lang/System:out	Ljava/io/PrintStream;
    //   845: aload 49
    //   847: iconst_2
    //   848: invokevirtual 54	weibo4android/org/json/JSONObject:toString	(I)Ljava/lang/String;
    //   851: invokevirtual 47	java/io/PrintStream:println	(Ljava/lang/String;)V
    //   854: getstatic 35	java/lang/System:out	Ljava/io/PrintStream;
    //   857: aload 49
    //   859: invokestatic 57	weibo4android/org/json/XML:toString	(Ljava/lang/Object;)Ljava/lang/String;
    //   862: invokevirtual 47	java/io/PrintStream:println	(Ljava/lang/String;)V
    //   865: getstatic 35	java/lang/System:out	Ljava/io/PrintStream;
    //   868: ldc 218
    //   870: invokevirtual 47	java/io/PrintStream:println	(Ljava/lang/String;)V
    //   873: new 37	weibo4android/org/json/JSONObject
    //   876: dup
    //   877: ldc 220
    //   879: invokespecial 51	weibo4android/org/json/JSONObject:<init>	(Ljava/lang/String;)V
    //   882: astore 50
    //   884: aload 50
    //   886: ldc 222
    //   888: ldc 224
    //   890: invokevirtual 214	weibo4android/org/json/JSONObject:put	(Ljava/lang/String;Ljava/lang/Object;)Lweibo4android/org/json/JSONObject;
    //   893: pop
    //   894: aload 50
    //   896: ldc 226
    //   898: new 37	weibo4android/org/json/JSONObject
    //   901: dup
    //   902: invokespecial 227	weibo4android/org/json/JSONObject:<init>	()V
    //   905: invokevirtual 214	weibo4android/org/json/JSONObject:put	(Ljava/lang/String;Ljava/lang/Object;)Lweibo4android/org/json/JSONObject;
    //   908: pop
    //   909: aload 50
    //   911: ldc 229
    //   913: new 73	weibo4android/org/json/JSONArray
    //   916: dup
    //   917: invokespecial 230	weibo4android/org/json/JSONArray:<init>	()V
    //   920: invokevirtual 214	weibo4android/org/json/JSONObject:put	(Ljava/lang/String;Ljava/lang/Object;)Lweibo4android/org/json/JSONObject;
    //   923: pop
    //   924: aload 50
    //   926: ldc 232
    //   928: bipush 57
    //   930: invokevirtual 235	weibo4android/org/json/JSONObject:put	(Ljava/lang/String;I)Lweibo4android/org/json/JSONObject;
    //   933: pop
    //   934: aload 50
    //   936: ldc 237
    //   938: ldc2_w 238
    //   941: invokevirtual 242	weibo4android/org/json/JSONObject:put	(Ljava/lang/String;D)Lweibo4android/org/json/JSONObject;
    //   944: pop
    //   945: aload 50
    //   947: ldc 164
    //   949: iconst_1
    //   950: invokevirtual 245	weibo4android/org/json/JSONObject:put	(Ljava/lang/String;Z)Lweibo4android/org/json/JSONObject;
    //   953: pop
    //   954: aload 50
    //   956: ldc 159
    //   958: iconst_0
    //   959: invokevirtual 245	weibo4android/org/json/JSONObject:put	(Ljava/lang/String;Z)Lweibo4android/org/json/JSONObject;
    //   962: pop
    //   963: aload 50
    //   965: ldc 157
    //   967: getstatic 249	weibo4android/org/json/JSONObject:NULL	Ljava/lang/Object;
    //   970: invokevirtual 214	weibo4android/org/json/JSONObject:put	(Ljava/lang/String;Ljava/lang/Object;)Lweibo4android/org/json/JSONObject;
    //   973: pop
    //   974: aload 50
    //   976: ldc 251
    //   978: ldc 164
    //   980: invokevirtual 214	weibo4android/org/json/JSONObject:put	(Ljava/lang/String;Ljava/lang/Object;)Lweibo4android/org/json/JSONObject;
    //   983: pop
    //   984: aload 50
    //   986: ldc 253
    //   988: dconst_0
    //   989: invokevirtual 242	weibo4android/org/json/JSONObject:put	(Ljava/lang/String;D)Lweibo4android/org/json/JSONObject;
    //   992: pop
    //   993: aload 50
    //   995: ldc 255
    //   997: ldc_w 257
    //   1000: invokevirtual 214	weibo4android/org/json/JSONObject:put	(Ljava/lang/String;Ljava/lang/Object;)Lweibo4android/org/json/JSONObject;
    //   1003: pop
    //   1004: aload 50
    //   1006: ldc_w 259
    //   1009: ldc_w 261
    //   1012: invokevirtual 214	weibo4android/org/json/JSONObject:put	(Ljava/lang/String;Ljava/lang/Object;)Lweibo4android/org/json/JSONObject;
    //   1015: pop
    //   1016: aload 50
    //   1018: ldc 113
    //   1020: invokevirtual 264	weibo4android/org/json/JSONObject:getJSONArray	(Ljava/lang/String;)Lweibo4android/org/json/JSONArray;
    //   1023: astore 63
    //   1025: aload 63
    //   1027: sipush 666
    //   1030: invokevirtual 267	weibo4android/org/json/JSONArray:put	(I)Lweibo4android/org/json/JSONArray;
    //   1033: pop
    //   1034: aload 63
    //   1036: ldc2_w 268
    //   1039: invokevirtual 272	weibo4android/org/json/JSONArray:put	(D)Lweibo4android/org/json/JSONArray;
    //   1042: pop
    //   1043: aload 63
    //   1045: ldc_w 274
    //   1048: invokevirtual 277	weibo4android/org/json/JSONArray:put	(Ljava/lang/Object;)Lweibo4android/org/json/JSONArray;
    //   1051: pop
    //   1052: aload 63
    //   1054: ldc_w 279
    //   1057: invokevirtual 277	weibo4android/org/json/JSONArray:put	(Ljava/lang/Object;)Lweibo4android/org/json/JSONArray;
    //   1060: pop
    //   1061: aload 63
    //   1063: iconst_1
    //   1064: invokevirtual 282	weibo4android/org/json/JSONArray:put	(Z)Lweibo4android/org/json/JSONArray;
    //   1067: pop
    //   1068: aload 63
    //   1070: iconst_0
    //   1071: invokevirtual 282	weibo4android/org/json/JSONArray:put	(Z)Lweibo4android/org/json/JSONArray;
    //   1074: pop
    //   1075: aload 63
    //   1077: new 73	weibo4android/org/json/JSONArray
    //   1080: dup
    //   1081: invokespecial 230	weibo4android/org/json/JSONArray:<init>	()V
    //   1084: invokevirtual 277	weibo4android/org/json/JSONArray:put	(Ljava/lang/Object;)Lweibo4android/org/json/JSONArray;
    //   1087: pop
    //   1088: aload 63
    //   1090: new 37	weibo4android/org/json/JSONObject
    //   1093: dup
    //   1094: invokespecial 227	weibo4android/org/json/JSONObject:<init>	()V
    //   1097: invokevirtual 277	weibo4android/org/json/JSONArray:put	(Ljava/lang/Object;)Lweibo4android/org/json/JSONArray;
    //   1100: pop
    //   1101: aload 50
    //   1103: ldc_w 284
    //   1106: aload 50
    //   1108: invokestatic 287	weibo4android/org/json/JSONObject:getNames	(Lweibo4android/org/json/JSONObject;)[Ljava/lang/String;
    //   1111: invokevirtual 214	weibo4android/org/json/JSONObject:put	(Ljava/lang/String;Ljava/lang/Object;)Lweibo4android/org/json/JSONObject;
    //   1114: pop
    //   1115: getstatic 35	java/lang/System:out	Ljava/io/PrintStream;
    //   1118: aload 50
    //   1120: iconst_4
    //   1121: invokevirtual 54	weibo4android/org/json/JSONObject:toString	(I)Ljava/lang/String;
    //   1124: invokevirtual 47	java/io/PrintStream:println	(Ljava/lang/String;)V
    //   1127: getstatic 35	java/lang/System:out	Ljava/io/PrintStream;
    //   1130: aload 50
    //   1132: invokestatic 57	weibo4android/org/json/XML:toString	(Ljava/lang/Object;)Ljava/lang/String;
    //   1135: invokevirtual 47	java/io/PrintStream:println	(Ljava/lang/String;)V
    //   1138: getstatic 35	java/lang/System:out	Ljava/io/PrintStream;
    //   1141: new 289	java/lang/StringBuilder
    //   1144: dup
    //   1145: invokespecial 290	java/lang/StringBuilder:<init>	()V
    //   1148: ldc_w 292
    //   1151: invokevirtual 296	java/lang/StringBuilder:append	(Ljava/lang/String;)Ljava/lang/StringBuilder;
    //   1154: aload 50
    //   1156: ldc 222
    //   1158: invokevirtual 300	weibo4android/org/json/JSONObject:getDouble	(Ljava/lang/String;)D
    //   1161: invokevirtual 303	java/lang/StringBuilder:append	(D)Ljava/lang/StringBuilder;
    //   1164: invokevirtual 304	java/lang/StringBuilder:toString	()Ljava/lang/String;
    //   1167: invokevirtual 47	java/io/PrintStream:println	(Ljava/lang/String;)V
    //   1170: getstatic 35	java/lang/System:out	Ljava/io/PrintStream;
    //   1173: new 289	java/lang/StringBuilder
    //   1176: dup
    //   1177: invokespecial 290	java/lang/StringBuilder:<init>	()V
    //   1180: ldc_w 306
    //   1183: invokevirtual 296	java/lang/StringBuilder:append	(Ljava/lang/String;)Ljava/lang/StringBuilder;
    //   1186: aload 50
    //   1188: ldc 251
    //   1190: invokevirtual 310	weibo4android/org/json/JSONObject:getBoolean	(Ljava/lang/String;)Z
    //   1193: invokevirtual 313	java/lang/StringBuilder:append	(Z)Ljava/lang/StringBuilder;
    //   1196: invokevirtual 304	java/lang/StringBuilder:toString	()Ljava/lang/String;
    //   1199: invokevirtual 47	java/io/PrintStream:println	(Ljava/lang/String;)V
    //   1202: getstatic 35	java/lang/System:out	Ljava/io/PrintStream;
    //   1205: new 289	java/lang/StringBuilder
    //   1208: dup
    //   1209: invokespecial 290	java/lang/StringBuilder:<init>	()V
    //   1212: ldc_w 315
    //   1215: invokevirtual 296	java/lang/StringBuilder:append	(Ljava/lang/String;)Ljava/lang/StringBuilder;
    //   1218: aload 50
    //   1220: ldc_w 317
    //   1223: invokevirtual 321	weibo4android/org/json/JSONObject:getString	(Ljava/lang/String;)Ljava/lang/String;
    //   1226: invokevirtual 296	java/lang/StringBuilder:append	(Ljava/lang/String;)Ljava/lang/StringBuilder;
    //   1229: invokevirtual 304	java/lang/StringBuilder:toString	()Ljava/lang/String;
    //   1232: invokevirtual 47	java/io/PrintStream:println	(Ljava/lang/String;)V
    //   1235: getstatic 35	java/lang/System:out	Ljava/io/PrintStream;
    //   1238: new 289	java/lang/StringBuilder
    //   1241: dup
    //   1242: invokespecial 290	java/lang/StringBuilder:<init>	()V
    //   1245: ldc_w 323
    //   1248: invokevirtual 296	java/lang/StringBuilder:append	(Ljava/lang/String;)Ljava/lang/StringBuilder;
    //   1251: aload 50
    //   1253: ldc 164
    //   1255: invokevirtual 321	weibo4android/org/json/JSONObject:getString	(Ljava/lang/String;)Ljava/lang/String;
    //   1258: invokevirtual 296	java/lang/StringBuilder:append	(Ljava/lang/String;)Ljava/lang/StringBuilder;
    //   1261: invokevirtual 304	java/lang/StringBuilder:toString	()Ljava/lang/String;
    //   1264: invokevirtual 47	java/io/PrintStream:println	(Ljava/lang/String;)V
    //   1267: getstatic 35	java/lang/System:out	Ljava/io/PrintStream;
    //   1270: new 289	java/lang/StringBuilder
    //   1273: dup
    //   1274: invokespecial 290	java/lang/StringBuilder:<init>	()V
    //   1277: ldc_w 325
    //   1280: invokevirtual 296	java/lang/StringBuilder:append	(Ljava/lang/String;)Ljava/lang/StringBuilder;
    //   1283: aload 50
    //   1285: ldc 113
    //   1287: invokevirtual 264	weibo4android/org/json/JSONObject:getJSONArray	(Ljava/lang/String;)Lweibo4android/org/json/JSONArray;
    //   1290: invokevirtual 328	java/lang/StringBuilder:append	(Ljava/lang/Object;)Ljava/lang/StringBuilder;
    //   1293: invokevirtual 304	java/lang/StringBuilder:toString	()Ljava/lang/String;
    //   1296: invokevirtual 47	java/io/PrintStream:println	(Ljava/lang/String;)V
    //   1299: getstatic 35	java/lang/System:out	Ljava/io/PrintStream;
    //   1302: new 289	java/lang/StringBuilder
    //   1305: dup
    //   1306: invokespecial 290	java/lang/StringBuilder:<init>	()V
    //   1309: ldc_w 330
    //   1312: invokevirtual 296	java/lang/StringBuilder:append	(Ljava/lang/String;)Ljava/lang/StringBuilder;
    //   1315: aload 50
    //   1317: ldc_w 332
    //   1320: invokevirtual 321	weibo4android/org/json/JSONObject:getString	(Ljava/lang/String;)Ljava/lang/String;
    //   1323: invokevirtual 296	java/lang/StringBuilder:append	(Ljava/lang/String;)Ljava/lang/StringBuilder;
    //   1326: invokevirtual 304	java/lang/StringBuilder:toString	()Ljava/lang/String;
    //   1329: invokevirtual 47	java/io/PrintStream:println	(Ljava/lang/String;)V
    //   1332: getstatic 35	java/lang/System:out	Ljava/io/PrintStream;
    //   1335: new 289	java/lang/StringBuilder
    //   1338: dup
    //   1339: invokespecial 290	java/lang/StringBuilder:<init>	()V
    //   1342: ldc_w 334
    //   1345: invokevirtual 296	java/lang/StringBuilder:append	(Ljava/lang/String;)Ljava/lang/StringBuilder;
    //   1348: aload 50
    //   1350: ldc_w 336
    //   1353: invokevirtual 340	weibo4android/org/json/JSONObject:getInt	(Ljava/lang/String;)I
    //   1356: invokevirtual 343	java/lang/StringBuilder:append	(I)Ljava/lang/StringBuilder;
    //   1359: invokevirtual 304	java/lang/StringBuilder:toString	()Ljava/lang/String;
    //   1362: invokevirtual 47	java/io/PrintStream:println	(Ljava/lang/String;)V
    //   1365: getstatic 35	java/lang/System:out	Ljava/io/PrintStream;
    //   1368: new 289	java/lang/StringBuilder
    //   1371: dup
    //   1372: invokespecial 290	java/lang/StringBuilder:<init>	()V
    //   1375: ldc_w 345
    //   1378: invokevirtual 296	java/lang/StringBuilder:append	(Ljava/lang/String;)Ljava/lang/StringBuilder;
    //   1381: aload 50
    //   1383: ldc_w 347
    //   1386: invokevirtual 350	weibo4android/org/json/JSONObject:optBoolean	(Ljava/lang/String;)Z
    //   1389: invokevirtual 313	java/lang/StringBuilder:append	(Z)Ljava/lang/StringBuilder;
    //   1392: invokevirtual 304	java/lang/StringBuilder:toString	()Ljava/lang/String;
    //   1395: invokevirtual 47	java/io/PrintStream:println	(Ljava/lang/String;)V
    //   1398: ldc_w 352
    //   1401: invokestatic 29	weibo4android/org/json/XML:toJSONObject	(Ljava/lang/String;)Lweibo4android/org/json/JSONObject;
    //   1404: astore 73
    //   1406: getstatic 35	java/lang/System:out	Ljava/io/PrintStream;
    //   1409: aload 73
    //   1411: iconst_2
    //   1412: invokevirtual 54	weibo4android/org/json/JSONObject:toString	(I)Ljava/lang/String;
    //   1415: invokevirtual 47	java/io/PrintStream:println	(Ljava/lang/String;)V
    //   1418: getstatic 35	java/lang/System:out	Ljava/io/PrintStream;
    //   1421: aload 73
    //   1423: invokestatic 57	weibo4android/org/json/XML:toString	(Ljava/lang/Object;)Ljava/lang/String;
    //   1426: invokevirtual 47	java/io/PrintStream:println	(Ljava/lang/String;)V
    //   1429: getstatic 35	java/lang/System:out	Ljava/io/PrintStream;
    //   1432: ldc 218
    //   1434: invokevirtual 47	java/io/PrintStream:println	(Ljava/lang/String;)V
    //   1437: ldc_w 352
    //   1440: invokestatic 71	weibo4android/org/json/JSONML:toJSONArray	(Ljava/lang/String;)Lweibo4android/org/json/JSONArray;
    //   1443: astore 74
    //   1445: getstatic 35	java/lang/System:out	Ljava/io/PrintStream;
    //   1448: aload 74
    //   1450: iconst_4
    //   1451: invokevirtual 74	weibo4android/org/json/JSONArray:toString	(I)Ljava/lang/String;
    //   1454: invokevirtual 47	java/io/PrintStream:println	(Ljava/lang/String;)V
    //   1457: getstatic 35	java/lang/System:out	Ljava/io/PrintStream;
    //   1460: aload 74
    //   1462: invokestatic 77	weibo4android/org/json/JSONML:toString	(Lweibo4android/org/json/JSONArray;)Ljava/lang/String;
    //   1465: invokevirtual 47	java/io/PrintStream:println	(Ljava/lang/String;)V
    //   1468: getstatic 35	java/lang/System:out	Ljava/io/PrintStream;
    //   1471: ldc 218
    //   1473: invokevirtual 47	java/io/PrintStream:println	(Ljava/lang/String;)V
    //   1476: ldc_w 354
    //   1479: invokestatic 71	weibo4android/org/json/JSONML:toJSONArray	(Ljava/lang/String;)Lweibo4android/org/json/JSONArray;
    //   1482: astore 75
    //   1484: getstatic 35	java/lang/System:out	Ljava/io/PrintStream;
    //   1487: aload 75
    //   1489: iconst_4
    //   1490: invokevirtual 74	weibo4android/org/json/JSONArray:toString	(I)Ljava/lang/String;
    //   1493: invokevirtual 47	java/io/PrintStream:println	(Ljava/lang/String;)V
    //   1496: getstatic 35	java/lang/System:out	Ljava/io/PrintStream;
    //   1499: aload 75
    //   1501: invokestatic 77	weibo4android/org/json/JSONML:toString	(Lweibo4android/org/json/JSONArray;)Ljava/lang/String;
    //   1504: invokevirtual 47	java/io/PrintStream:println	(Ljava/lang/String;)V
    //   1507: getstatic 35	java/lang/System:out	Ljava/io/PrintStream;
    //   1510: ldc 218
    //   1512: invokevirtual 47	java/io/PrintStream:println	(Ljava/lang/String;)V
    //   1515: ldc_w 356
    //   1518: invokestatic 29	weibo4android/org/json/XML:toJSONObject	(Ljava/lang/String;)Lweibo4android/org/json/JSONObject;
    //   1521: astore 76
    //   1523: getstatic 35	java/lang/System:out	Ljava/io/PrintStream;
    //   1526: aload 76
    //   1528: iconst_2
    //   1529: invokevirtual 54	weibo4android/org/json/JSONObject:toString	(I)Ljava/lang/String;
    //   1532: invokevirtual 47	java/io/PrintStream:println	(Ljava/lang/String;)V
    //   1535: getstatic 35	java/lang/System:out	Ljava/io/PrintStream;
    //   1538: aload 76
    //   1540: invokestatic 57	weibo4android/org/json/XML:toString	(Ljava/lang/Object;)Ljava/lang/String;
    //   1543: invokevirtual 47	java/io/PrintStream:println	(Ljava/lang/String;)V
    //   1546: getstatic 35	java/lang/System:out	Ljava/io/PrintStream;
    //   1549: ldc 218
    //   1551: invokevirtual 47	java/io/PrintStream:println	(Ljava/lang/String;)V
    //   1554: ldc_w 356
    //   1557: invokestatic 71	weibo4android/org/json/JSONML:toJSONArray	(Ljava/lang/String;)Lweibo4android/org/json/JSONArray;
    //   1560: astore 77
    //   1562: getstatic 35	java/lang/System:out	Ljava/io/PrintStream;
    //   1565: aload 77
    //   1567: iconst_4
    //   1568: invokevirtual 74	weibo4android/org/json/JSONArray:toString	(I)Ljava/lang/String;
    //   1571: invokevirtual 47	java/io/PrintStream:println	(Ljava/lang/String;)V
    //   1574: getstatic 35	java/lang/System:out	Ljava/io/PrintStream;
    //   1577: aload 77
    //   1579: invokestatic 77	weibo4android/org/json/JSONML:toString	(Lweibo4android/org/json/JSONArray;)Ljava/lang/String;
    //   1582: invokevirtual 47	java/io/PrintStream:println	(Ljava/lang/String;)V
    //   1585: getstatic 35	java/lang/System:out	Ljava/io/PrintStream;
    //   1588: ldc 218
    //   1590: invokevirtual 47	java/io/PrintStream:println	(Ljava/lang/String;)V
    //   1593: ldc_w 358
    //   1596: invokestatic 29	weibo4android/org/json/XML:toJSONObject	(Ljava/lang/String;)Lweibo4android/org/json/JSONObject;
    //   1599: astore 78
    //   1601: getstatic 35	java/lang/System:out	Ljava/io/PrintStream;
    //   1604: aload 78
    //   1606: iconst_2
    //   1607: invokevirtual 54	weibo4android/org/json/JSONObject:toString	(I)Ljava/lang/String;
    //   1610: invokevirtual 47	java/io/PrintStream:println	(Ljava/lang/String;)V
    //   1613: getstatic 35	java/lang/System:out	Ljava/io/PrintStream;
    //   1616: aload 78
    //   1618: invokestatic 57	weibo4android/org/json/XML:toString	(Ljava/lang/Object;)Ljava/lang/String;
    //   1621: invokevirtual 47	java/io/PrintStream:println	(Ljava/lang/String;)V
    //   1624: getstatic 35	java/lang/System:out	Ljava/io/PrintStream;
    //   1627: ldc 218
    //   1629: invokevirtual 47	java/io/PrintStream:println	(Ljava/lang/String;)V
    //   1632: ldc_w 360
    //   1635: invokestatic 29	weibo4android/org/json/XML:toJSONObject	(Ljava/lang/String;)Lweibo4android/org/json/JSONObject;
    //   1638: astore 79
    //   1640: getstatic 35	java/lang/System:out	Ljava/io/PrintStream;
    //   1643: aload 79
    //   1645: iconst_2
    //   1646: invokevirtual 54	weibo4android/org/json/JSONObject:toString	(I)Ljava/lang/String;
    //   1649: invokevirtual 47	java/io/PrintStream:println	(Ljava/lang/String;)V
    //   1652: getstatic 35	java/lang/System:out	Ljava/io/PrintStream;
    //   1655: aload 79
    //   1657: invokestatic 57	weibo4android/org/json/XML:toString	(Ljava/lang/Object;)Ljava/lang/String;
    //   1660: invokevirtual 47	java/io/PrintStream:println	(Ljava/lang/String;)V
    //   1663: getstatic 35	java/lang/System:out	Ljava/io/PrintStream;
    //   1666: ldc 218
    //   1668: invokevirtual 47	java/io/PrintStream:println	(Ljava/lang/String;)V
    //   1671: ldc_w 362
    //   1674: invokestatic 29	weibo4android/org/json/XML:toJSONObject	(Ljava/lang/String;)Lweibo4android/org/json/JSONObject;
    //   1677: astore 80
    //   1679: getstatic 35	java/lang/System:out	Ljava/io/PrintStream;
    //   1682: aload 80
    //   1684: iconst_2
    //   1685: invokevirtual 54	weibo4android/org/json/JSONObject:toString	(I)Ljava/lang/String;
    //   1688: invokevirtual 47	java/io/PrintStream:println	(Ljava/lang/String;)V
    //   1691: getstatic 35	java/lang/System:out	Ljava/io/PrintStream;
    //   1694: aload 80
    //   1696: invokestatic 57	weibo4android/org/json/XML:toString	(Ljava/lang/Object;)Ljava/lang/String;
    //   1699: invokevirtual 47	java/io/PrintStream:println	(Ljava/lang/String;)V
    //   1702: getstatic 35	java/lang/System:out	Ljava/io/PrintStream;
    //   1705: ldc 218
    //   1707: invokevirtual 47	java/io/PrintStream:println	(Ljava/lang/String;)V
    //   1710: ldc_w 364
    //   1713: invokestatic 29	weibo4android/org/json/XML:toJSONObject	(Ljava/lang/String;)Lweibo4android/org/json/JSONObject;
    //   1716: astore 81
    //   1718: getstatic 35	java/lang/System:out	Ljava/io/PrintStream;
    //   1721: aload 81
    //   1723: invokevirtual 41	weibo4android/org/json/JSONObject:toString	()Ljava/lang/String;
    //   1726: invokevirtual 47	java/io/PrintStream:println	(Ljava/lang/String;)V
    //   1729: getstatic 35	java/lang/System:out	Ljava/io/PrintStream;
    //   1732: aload 81
    //   1734: invokestatic 57	weibo4android/org/json/XML:toString	(Ljava/lang/Object;)Ljava/lang/String;
    //   1737: invokevirtual 47	java/io/PrintStream:println	(Ljava/lang/String;)V
    //   1740: getstatic 35	java/lang/System:out	Ljava/io/PrintStream;
    //   1743: ldc 218
    //   1745: invokevirtual 47	java/io/PrintStream:println	(Ljava/lang/String;)V
    //   1748: ldc_w 366
    //   1751: invokestatic 29	weibo4android/org/json/XML:toJSONObject	(Ljava/lang/String;)Lweibo4android/org/json/JSONObject;
    //   1754: astore 82
    //   1756: getstatic 35	java/lang/System:out	Ljava/io/PrintStream;
    //   1759: aload 82
    //   1761: iconst_2
    //   1762: invokevirtual 54	weibo4android/org/json/JSONObject:toString	(I)Ljava/lang/String;
    //   1765: invokevirtual 47	java/io/PrintStream:println	(Ljava/lang/String;)V
    //   1768: getstatic 35	java/lang/System:out	Ljava/io/PrintStream;
    //   1771: aload 82
    //   1773: invokestatic 57	weibo4android/org/json/XML:toString	(Ljava/lang/Object;)Ljava/lang/String;
    //   1776: invokevirtual 47	java/io/PrintStream:println	(Ljava/lang/String;)V
    //   1779: getstatic 35	java/lang/System:out	Ljava/io/PrintStream;
    //   1782: ldc 218
    //   1784: invokevirtual 47	java/io/PrintStream:println	(Ljava/lang/String;)V
    //   1787: ldc_w 368
    //   1790: invokestatic 371	weibo4android/org/json/HTTP:toJSONObject	(Ljava/lang/String;)Lweibo4android/org/json/JSONObject;
    //   1793: astore 83
    //   1795: getstatic 35	java/lang/System:out	Ljava/io/PrintStream;
    //   1798: aload 83
    //   1800: iconst_2
    //   1801: invokevirtual 54	weibo4android/org/json/JSONObject:toString	(I)Ljava/lang/String;
    //   1804: invokevirtual 47	java/io/PrintStream:println	(Ljava/lang/String;)V
    //   1807: getstatic 35	java/lang/System:out	Ljava/io/PrintStream;
    //   1810: aload 83
    //   1812: invokestatic 372	weibo4android/org/json/HTTP:toString	(Lweibo4android/org/json/JSONObject;)Ljava/lang/String;
    //   1815: invokevirtual 47	java/io/PrintStream:println	(Ljava/lang/String;)V
    //   1818: getstatic 35	java/lang/System:out	Ljava/io/PrintStream;
    //   1821: ldc 218
    //   1823: invokevirtual 47	java/io/PrintStream:println	(Ljava/lang/String;)V
    //   1826: ldc_w 374
    //   1829: invokestatic 371	weibo4android/org/json/HTTP:toJSONObject	(Ljava/lang/String;)Lweibo4android/org/json/JSONObject;
    //   1832: astore 84
    //   1834: getstatic 35	java/lang/System:out	Ljava/io/PrintStream;
    //   1837: aload 84
    //   1839: iconst_2
    //   1840: invokevirtual 54	weibo4android/org/json/JSONObject:toString	(I)Ljava/lang/String;
    //   1843: invokevirtual 47	java/io/PrintStream:println	(Ljava/lang/String;)V
    //   1846: getstatic 35	java/lang/System:out	Ljava/io/PrintStream;
    //   1849: aload 84
    //   1851: invokestatic 372	weibo4android/org/json/HTTP:toString	(Lweibo4android/org/json/JSONObject;)Ljava/lang/String;
    //   1854: invokevirtual 47	java/io/PrintStream:println	(Ljava/lang/String;)V
    //   1857: getstatic 35	java/lang/System:out	Ljava/io/PrintStream;
    //   1860: ldc 218
    //   1862: invokevirtual 47	java/io/PrintStream:println	(Ljava/lang/String;)V
    //   1865: new 37	weibo4android/org/json/JSONObject
    //   1868: dup
    //   1869: ldc_w 376
    //   1872: invokespecial 51	weibo4android/org/json/JSONObject:<init>	(Ljava/lang/String;)V
    //   1875: astore 85
    //   1877: getstatic 35	java/lang/System:out	Ljava/io/PrintStream;
    //   1880: aload 85
    //   1882: iconst_2
    //   1883: invokevirtual 54	weibo4android/org/json/JSONObject:toString	(I)Ljava/lang/String;
    //   1886: invokevirtual 47	java/io/PrintStream:println	(Ljava/lang/String;)V
    //   1889: getstatic 35	java/lang/System:out	Ljava/io/PrintStream;
    //   1892: new 289	java/lang/StringBuilder
    //   1895: dup
    //   1896: invokespecial 290	java/lang/StringBuilder:<init>	()V
    //   1899: ldc_w 378
    //   1902: invokevirtual 296	java/lang/StringBuilder:append	(Ljava/lang/String;)Ljava/lang/StringBuilder;
    //   1905: aload 85
    //   1907: ldc_w 380
    //   1910: invokevirtual 383	weibo4android/org/json/JSONObject:isNull	(Ljava/lang/String;)Z
    //   1913: invokevirtual 313	java/lang/StringBuilder:append	(Z)Ljava/lang/StringBuilder;
    //   1916: invokevirtual 304	java/lang/StringBuilder:toString	()Ljava/lang/String;
    //   1919: invokevirtual 47	java/io/PrintStream:println	(Ljava/lang/String;)V
    //   1922: getstatic 35	java/lang/System:out	Ljava/io/PrintStream;
    //   1925: new 289	java/lang/StringBuilder
    //   1928: dup
    //   1929: invokespecial 290	java/lang/StringBuilder:<init>	()V
    //   1932: ldc_w 385
    //   1935: invokevirtual 296	java/lang/StringBuilder:append	(Ljava/lang/String;)Ljava/lang/StringBuilder;
    //   1938: aload 85
    //   1940: ldc_w 380
    //   1943: invokevirtual 388	weibo4android/org/json/JSONObject:has	(Ljava/lang/String;)Z
    //   1946: invokevirtual 313	java/lang/StringBuilder:append	(Z)Ljava/lang/StringBuilder;
    //   1949: invokevirtual 304	java/lang/StringBuilder:toString	()Ljava/lang/String;
    //   1952: invokevirtual 47	java/io/PrintStream:println	(Ljava/lang/String;)V
    //   1955: getstatic 35	java/lang/System:out	Ljava/io/PrintStream;
    //   1958: aload 85
    //   1960: invokestatic 57	weibo4android/org/json/XML:toString	(Ljava/lang/Object;)Ljava/lang/String;
    //   1963: invokevirtual 47	java/io/PrintStream:println	(Ljava/lang/String;)V
    //   1966: getstatic 35	java/lang/System:out	Ljava/io/PrintStream;
    //   1969: aload 85
    //   1971: invokestatic 372	weibo4android/org/json/HTTP:toString	(Lweibo4android/org/json/JSONObject;)Ljava/lang/String;
    //   1974: invokevirtual 47	java/io/PrintStream:println	(Ljava/lang/String;)V
    //   1977: getstatic 35	java/lang/System:out	Ljava/io/PrintStream;
    //   1980: ldc 218
    //   1982: invokevirtual 47	java/io/PrintStream:println	(Ljava/lang/String;)V
    //   1985: ldc_w 390
    //   1988: invokestatic 29	weibo4android/org/json/XML:toJSONObject	(Ljava/lang/String;)Lweibo4android/org/json/JSONObject;
    //   1991: astore 86
    //   1993: getstatic 35	java/lang/System:out	Ljava/io/PrintStream;
    //   1996: aload 86
    //   1998: iconst_2
    //   1999: invokevirtual 54	weibo4android/org/json/JSONObject:toString	(I)Ljava/lang/String;
    //   2002: invokevirtual 47	java/io/PrintStream:println	(Ljava/lang/String;)V
    //   2005: getstatic 35	java/lang/System:out	Ljava/io/PrintStream;
    //   2008: aload 86
    //   2010: invokestatic 57	weibo4android/org/json/XML:toString	(Ljava/lang/Object;)Ljava/lang/String;
    //   2013: invokevirtual 47	java/io/PrintStream:println	(Ljava/lang/String;)V
    //   2016: getstatic 35	java/lang/System:out	Ljava/io/PrintStream;
    //   2019: ldc 218
    //   2021: invokevirtual 47	java/io/PrintStream:println	(Ljava/lang/String;)V
    //   2024: new 37	weibo4android/org/json/JSONObject
    //   2027: dup
    //   2028: ldc_w 392
    //   2031: invokespecial 51	weibo4android/org/json/JSONObject:<init>	(Ljava/lang/String;)V
    //   2034: astore 87
    //   2036: getstatic 35	java/lang/System:out	Ljava/io/PrintStream;
    //   2039: aload 87
    //   2041: iconst_2
    //   2042: invokevirtual 54	weibo4android/org/json/JSONObject:toString	(I)Ljava/lang/String;
    //   2045: invokevirtual 47	java/io/PrintStream:println	(Ljava/lang/String;)V
    //   2048: getstatic 35	java/lang/System:out	Ljava/io/PrintStream;
    //   2051: aload 87
    //   2053: invokestatic 57	weibo4android/org/json/XML:toString	(Ljava/lang/Object;)Ljava/lang/String;
    //   2056: invokevirtual 47	java/io/PrintStream:println	(Ljava/lang/String;)V
    //   2059: getstatic 35	java/lang/System:out	Ljava/io/PrintStream;
    //   2062: ldc 218
    //   2064: invokevirtual 47	java/io/PrintStream:println	(Ljava/lang/String;)V
    //   2067: ldc_w 394
    //   2070: invokestatic 397	weibo4android/org/json/CookieList:toJSONObject	(Ljava/lang/String;)Lweibo4android/org/json/JSONObject;
    //   2073: astore 88
    //   2075: getstatic 35	java/lang/System:out	Ljava/io/PrintStream;
    //   2078: aload 88
    //   2080: iconst_2
    //   2081: invokevirtual 54	weibo4android/org/json/JSONObject:toString	(I)Ljava/lang/String;
    //   2084: invokevirtual 47	java/io/PrintStream:println	(Ljava/lang/String;)V
    //   2087: getstatic 35	java/lang/System:out	Ljava/io/PrintStream;
    //   2090: aload 88
    //   2092: invokestatic 398	weibo4android/org/json/CookieList:toString	(Lweibo4android/org/json/JSONObject;)Ljava/lang/String;
    //   2095: invokevirtual 47	java/io/PrintStream:println	(Ljava/lang/String;)V
    //   2098: getstatic 35	java/lang/System:out	Ljava/io/PrintStream;
    //   2101: ldc 218
    //   2103: invokevirtual 47	java/io/PrintStream:println	(Ljava/lang/String;)V
    //   2106: ldc_w 400
    //   2109: invokestatic 403	weibo4android/org/json/Cookie:toJSONObject	(Ljava/lang/String;)Lweibo4android/org/json/JSONObject;
    //   2112: astore 89
    //   2114: getstatic 35	java/lang/System:out	Ljava/io/PrintStream;
    //   2117: aload 89
    //   2119: iconst_2
    //   2120: invokevirtual 54	weibo4android/org/json/JSONObject:toString	(I)Ljava/lang/String;
    //   2123: invokevirtual 47	java/io/PrintStream:println	(Ljava/lang/String;)V
    //   2126: getstatic 35	java/lang/System:out	Ljava/io/PrintStream;
    //   2129: aload 89
    //   2131: invokestatic 404	weibo4android/org/json/Cookie:toString	(Lweibo4android/org/json/JSONObject;)Ljava/lang/String;
    //   2134: invokevirtual 47	java/io/PrintStream:println	(Ljava/lang/String;)V
    //   2137: getstatic 35	java/lang/System:out	Ljava/io/PrintStream;
    //   2140: ldc 218
    //   2142: invokevirtual 47	java/io/PrintStream:println	(Ljava/lang/String;)V
    //   2145: new 37	weibo4android/org/json/JSONObject
    //   2148: dup
    //   2149: ldc_w 406
    //   2152: invokespecial 51	weibo4android/org/json/JSONObject:<init>	(Ljava/lang/String;)V
    //   2155: astore 90
    //   2157: getstatic 35	java/lang/System:out	Ljava/io/PrintStream;
    //   2160: aload 90
    //   2162: invokevirtual 41	weibo4android/org/json/JSONObject:toString	()Ljava/lang/String;
    //   2165: invokevirtual 47	java/io/PrintStream:println	(Ljava/lang/String;)V
    //   2168: getstatic 35	java/lang/System:out	Ljava/io/PrintStream;
    //   2171: ldc 218
    //   2173: invokevirtual 47	java/io/PrintStream:println	(Ljava/lang/String;)V
    //   2176: new 408	weibo4android/org/json/JSONTokener
    //   2179: dup
    //   2180: ldc_w 410
    //   2183: invokespecial 411	weibo4android/org/json/JSONTokener:<init>	(Ljava/lang/String;)V
    //   2186: astore 91
    //   2188: new 37	weibo4android/org/json/JSONObject
    //   2191: dup
    //   2192: aload 91
    //   2194: invokespecial 414	weibo4android/org/json/JSONObject:<init>	(Lweibo4android/org/json/JSONTokener;)V
    //   2197: astore 92
    //   2199: getstatic 35	java/lang/System:out	Ljava/io/PrintStream;
    //   2202: aload 92
    //   2204: invokevirtual 41	weibo4android/org/json/JSONObject:toString	()Ljava/lang/String;
    //   2207: invokevirtual 47	java/io/PrintStream:println	(Ljava/lang/String;)V
    //   2210: getstatic 35	java/lang/System:out	Ljava/io/PrintStream;
    //   2213: new 289	java/lang/StringBuilder
    //   2216: dup
    //   2217: invokespecial 290	java/lang/StringBuilder:<init>	()V
    //   2220: ldc_w 416
    //   2223: invokevirtual 296	java/lang/StringBuilder:append	(Ljava/lang/String;)Ljava/lang/StringBuilder;
    //   2226: aload 92
    //   2228: ldc_w 418
    //   2231: invokevirtual 421	weibo4android/org/json/JSONObject:optInt	(Ljava/lang/String;)I
    //   2234: invokevirtual 343	java/lang/StringBuilder:append	(I)Ljava/lang/StringBuilder;
    //   2237: invokevirtual 304	java/lang/StringBuilder:toString	()Ljava/lang/String;
    //   2240: invokevirtual 47	java/io/PrintStream:println	(Ljava/lang/String;)V
    //   2243: aload 91
    //   2245: bipush 123
    //   2247: invokevirtual 425	weibo4android/org/json/JSONTokener:skipTo	(C)C
    //   2250: istore 93
    //   2252: getstatic 35	java/lang/System:out	Ljava/io/PrintStream;
    //   2255: iload 93
    //   2257: invokevirtual 428	java/io/PrintStream:println	(I)V
    //   2260: new 37	weibo4android/org/json/JSONObject
    //   2263: dup
    //   2264: aload 91
    //   2266: invokespecial 414	weibo4android/org/json/JSONObject:<init>	(Lweibo4android/org/json/JSONTokener;)V
    //   2269: astore 94
    //   2271: getstatic 35	java/lang/System:out	Ljava/io/PrintStream;
    //   2274: aload 94
    //   2276: invokevirtual 41	weibo4android/org/json/JSONObject:toString	()Ljava/lang/String;
    //   2279: invokevirtual 47	java/io/PrintStream:println	(Ljava/lang/String;)V
    //   2282: getstatic 35	java/lang/System:out	Ljava/io/PrintStream;
    //   2285: ldc 218
    //   2287: invokevirtual 47	java/io/PrintStream:println	(Ljava/lang/String;)V
    //   2290: ldc_w 430
    //   2293: invokestatic 433	weibo4android/org/json/CDL:toJSONArray	(Ljava/lang/String;)Lweibo4android/org/json/JSONArray;
    //   2296: astore 95
    //   2298: getstatic 35	java/lang/System:out	Ljava/io/PrintStream;
    //   2301: aload 95
    //   2303: invokestatic 434	weibo4android/org/json/CDL:toString	(Lweibo4android/org/json/JSONArray;)Ljava/lang/String;
    //   2306: invokevirtual 47	java/io/PrintStream:println	(Ljava/lang/String;)V
    //   2309: getstatic 35	java/lang/System:out	Ljava/io/PrintStream;
    //   2312: ldc 218
    //   2314: invokevirtual 47	java/io/PrintStream:println	(Ljava/lang/String;)V
    //   2317: getstatic 35	java/lang/System:out	Ljava/io/PrintStream;
    //   2320: aload 95
    //   2322: iconst_4
    //   2323: invokevirtual 74	weibo4android/org/json/JSONArray:toString	(I)Ljava/lang/String;
    //   2326: invokevirtual 47	java/io/PrintStream:println	(Ljava/lang/String;)V
    //   2329: getstatic 35	java/lang/System:out	Ljava/io/PrintStream;
    //   2332: ldc 218
    //   2334: invokevirtual 47	java/io/PrintStream:println	(Ljava/lang/String;)V
    //   2337: new 73	weibo4android/org/json/JSONArray
    //   2340: dup
    //   2341: ldc_w 436
    //   2344: invokespecial 195	weibo4android/org/json/JSONArray:<init>	(Ljava/lang/String;)V
    //   2347: astore 96
    //   2349: getstatic 35	java/lang/System:out	Ljava/io/PrintStream;
    //   2352: aload 96
    //   2354: invokevirtual 197	weibo4android/org/json/JSONArray:toString	()Ljava/lang/String;
    //   2357: invokevirtual 47	java/io/PrintStream:println	(Ljava/lang/String;)V
    //   2360: getstatic 35	java/lang/System:out	Ljava/io/PrintStream;
    //   2363: ldc 218
    //   2365: invokevirtual 47	java/io/PrintStream:println	(Ljava/lang/String;)V
    //   2368: getstatic 35	java/lang/System:out	Ljava/io/PrintStream;
    //   2371: aload 96
    //   2373: invokestatic 57	weibo4android/org/json/XML:toString	(Ljava/lang/Object;)Ljava/lang/String;
    //   2376: invokevirtual 47	java/io/PrintStream:println	(Ljava/lang/String;)V
    //   2379: getstatic 35	java/lang/System:out	Ljava/io/PrintStream;
    //   2382: ldc 218
    //   2384: invokevirtual 47	java/io/PrintStream:println	(Ljava/lang/String;)V
    //   2387: new 37	weibo4android/org/json/JSONObject
    //   2390: dup
    //   2391: ldc_w 438
    //   2394: invokespecial 51	weibo4android/org/json/JSONObject:<init>	(Ljava/lang/String;)V
    //   2397: astore 97
    //   2399: getstatic 35	java/lang/System:out	Ljava/io/PrintStream;
    //   2402: aload 97
    //   2404: iconst_4
    //   2405: invokevirtual 54	weibo4android/org/json/JSONObject:toString	(I)Ljava/lang/String;
    //   2408: invokevirtual 47	java/io/PrintStream:println	(Ljava/lang/String;)V
    //   2411: getstatic 35	java/lang/System:out	Ljava/io/PrintStream;
    //   2414: ldc 218
    //   2416: invokevirtual 47	java/io/PrintStream:println	(Ljava/lang/String;)V
    //   2419: aload 97
    //   2421: ldc 164
    //   2423: invokevirtual 310	weibo4android/org/json/JSONObject:getBoolean	(Ljava/lang/String;)Z
    //   2426: ifeq +22 -> 2448
    //   2429: aload 97
    //   2431: ldc 159
    //   2433: invokevirtual 310	weibo4android/org/json/JSONObject:getBoolean	(Ljava/lang/String;)Z
    //   2436: ifne +12 -> 2448
    //   2439: getstatic 35	java/lang/System:out	Ljava/io/PrintStream;
    //   2442: ldc_w 440
    //   2445: invokevirtual 47	java/io/PrintStream:println	(Ljava/lang/String;)V
    //   2448: getstatic 35	java/lang/System:out	Ljava/io/PrintStream;
    //   2451: ldc 218
    //   2453: invokevirtual 47	java/io/PrintStream:println	(Ljava/lang/String;)V
    //   2456: new 37	weibo4android/org/json/JSONObject
    //   2459: dup
    //   2460: aload 97
    //   2462: iconst_4
    //   2463: anewarray 199	java/lang/String
    //   2466: dup
    //   2467: iconst_0
    //   2468: ldc_w 442
    //   2471: aastore
    //   2472: dup
    //   2473: iconst_1
    //   2474: ldc_w 444
    //   2477: aastore
    //   2478: dup
    //   2479: iconst_2
    //   2480: ldc_w 446
    //   2483: aastore
    //   2484: dup
    //   2485: iconst_3
    //   2486: ldc_w 448
    //   2489: aastore
    //   2490: invokespecial 451	weibo4android/org/json/JSONObject:<init>	(Lweibo4android/org/json/JSONObject;[Ljava/lang/String;)V
    //   2493: astore 98
    //   2495: getstatic 35	java/lang/System:out	Ljava/io/PrintStream;
    //   2498: aload 98
    //   2500: iconst_4
    //   2501: invokevirtual 54	weibo4android/org/json/JSONObject:toString	(I)Ljava/lang/String;
    //   2504: invokevirtual 47	java/io/PrintStream:println	(Ljava/lang/String;)V
    //   2507: getstatic 35	java/lang/System:out	Ljava/io/PrintStream;
    //   2510: ldc 218
    //   2512: invokevirtual 47	java/io/PrintStream:println	(Ljava/lang/String;)V
    //   2515: getstatic 35	java/lang/System:out	Ljava/io/PrintStream;
    //   2518: new 88	weibo4android/org/json/JSONStringer
    //   2521: dup
    //   2522: invokespecial 89	weibo4android/org/json/JSONStringer:<init>	()V
    //   2525: invokevirtual 143	weibo4android/org/json/JSONStringer:array	()Lweibo4android/org/json/JSONWriter;
    //   2528: aload 96
    //   2530: invokevirtual 107	weibo4android/org/json/JSONWriter:value	(Ljava/lang/Object;)Lweibo4android/org/json/JSONWriter;
    //   2533: aload 98
    //   2535: invokevirtual 107	weibo4android/org/json/JSONWriter:value	(Ljava/lang/Object;)Lweibo4android/org/json/JSONWriter;
    //   2538: invokevirtual 131	weibo4android/org/json/JSONWriter:endArray	()Lweibo4android/org/json/JSONWriter;
    //   2541: invokevirtual 453	java/io/PrintStream:println	(Ljava/lang/Object;)V
    //   2544: new 37	weibo4android/org/json/JSONObject
    //   2547: dup
    //   2548: ldc_w 455
    //   2551: invokespecial 51	weibo4android/org/json/JSONObject:<init>	(Ljava/lang/String;)V
    //   2554: astore 99
    //   2556: getstatic 35	java/lang/System:out	Ljava/io/PrintStream;
    //   2559: aload 99
    //   2561: iconst_4
    //   2562: invokevirtual 54	weibo4android/org/json/JSONObject:toString	(I)Ljava/lang/String;
    //   2565: invokevirtual 47	java/io/PrintStream:println	(Ljava/lang/String;)V
    //   2568: getstatic 35	java/lang/System:out	Ljava/io/PrintStream;
    //   2571: ldc_w 457
    //   2574: invokevirtual 47	java/io/PrintStream:println	(Ljava/lang/String;)V
    //   2577: getstatic 35	java/lang/System:out	Ljava/io/PrintStream;
    //   2580: new 289	java/lang/StringBuilder
    //   2583: dup
    //   2584: invokespecial 290	java/lang/StringBuilder:<init>	()V
    //   2587: ldc_w 459
    //   2590: invokevirtual 296	java/lang/StringBuilder:append	(Ljava/lang/String;)Ljava/lang/StringBuilder;
    //   2593: aload 99
    //   2595: ldc 232
    //   2597: invokevirtual 340	weibo4android/org/json/JSONObject:getInt	(Ljava/lang/String;)I
    //   2600: invokevirtual 343	java/lang/StringBuilder:append	(I)Ljava/lang/StringBuilder;
    //   2603: invokevirtual 304	java/lang/StringBuilder:toString	()Ljava/lang/String;
    //   2606: invokevirtual 47	java/io/PrintStream:println	(Ljava/lang/String;)V
    //   2609: getstatic 35	java/lang/System:out	Ljava/io/PrintStream;
    //   2612: new 289	java/lang/StringBuilder
    //   2615: dup
    //   2616: invokespecial 290	java/lang/StringBuilder:<init>	()V
    //   2619: ldc_w 461
    //   2622: invokevirtual 296	java/lang/StringBuilder:append	(Ljava/lang/String;)Ljava/lang/StringBuilder;
    //   2625: aload 99
    //   2627: ldc 179
    //   2629: invokevirtual 340	weibo4android/org/json/JSONObject:getInt	(Ljava/lang/String;)I
    //   2632: invokevirtual 343	java/lang/StringBuilder:append	(I)Ljava/lang/StringBuilder;
    //   2635: invokevirtual 304	java/lang/StringBuilder:toString	()Ljava/lang/String;
    //   2638: invokevirtual 47	java/io/PrintStream:println	(Ljava/lang/String;)V
    //   2641: getstatic 35	java/lang/System:out	Ljava/io/PrintStream;
    //   2644: new 289	java/lang/StringBuilder
    //   2647: dup
    //   2648: invokespecial 290	java/lang/StringBuilder:<init>	()V
    //   2651: ldc_w 463
    //   2654: invokevirtual 296	java/lang/StringBuilder:append	(Ljava/lang/String;)Ljava/lang/StringBuilder;
    //   2657: aload 99
    //   2659: ldc_w 465
    //   2662: invokevirtual 340	weibo4android/org/json/JSONObject:getInt	(Ljava/lang/String;)I
    //   2665: invokevirtual 343	java/lang/StringBuilder:append	(I)Ljava/lang/StringBuilder;
    //   2668: invokevirtual 304	java/lang/StringBuilder:toString	()Ljava/lang/String;
    //   2671: invokevirtual 47	java/io/PrintStream:println	(Ljava/lang/String;)V
    //   2674: getstatic 35	java/lang/System:out	Ljava/io/PrintStream;
    //   2677: new 289	java/lang/StringBuilder
    //   2680: dup
    //   2681: invokespecial 290	java/lang/StringBuilder:<init>	()V
    //   2684: ldc_w 467
    //   2687: invokevirtual 296	java/lang/StringBuilder:append	(Ljava/lang/String;)Ljava/lang/StringBuilder;
    //   2690: aload 99
    //   2692: ldc 237
    //   2694: invokevirtual 340	weibo4android/org/json/JSONObject:getInt	(Ljava/lang/String;)I
    //   2697: invokevirtual 343	java/lang/StringBuilder:append	(I)Ljava/lang/StringBuilder;
    //   2700: invokevirtual 304	java/lang/StringBuilder:toString	()Ljava/lang/String;
    //   2703: invokevirtual 47	java/io/PrintStream:println	(Ljava/lang/String;)V
    //   2706: getstatic 35	java/lang/System:out	Ljava/io/PrintStream;
    //   2709: new 289	java/lang/StringBuilder
    //   2712: dup
    //   2713: invokespecial 290	java/lang/StringBuilder:<init>	()V
    //   2716: ldc_w 469
    //   2719: invokevirtual 296	java/lang/StringBuilder:append	(Ljava/lang/String;)Ljava/lang/StringBuilder;
    //   2722: aload 99
    //   2724: ldc_w 471
    //   2727: invokevirtual 340	weibo4android/org/json/JSONObject:getInt	(Ljava/lang/String;)I
    //   2730: invokevirtual 343	java/lang/StringBuilder:append	(I)Ljava/lang/StringBuilder;
    //   2733: invokevirtual 304	java/lang/StringBuilder:toString	()Ljava/lang/String;
    //   2736: invokevirtual 47	java/io/PrintStream:println	(Ljava/lang/String;)V
    //   2739: getstatic 35	java/lang/System:out	Ljava/io/PrintStream;
    //   2742: ldc_w 473
    //   2745: invokevirtual 47	java/io/PrintStream:println	(Ljava/lang/String;)V
    //   2748: getstatic 35	java/lang/System:out	Ljava/io/PrintStream;
    //   2751: new 289	java/lang/StringBuilder
    //   2754: dup
    //   2755: invokespecial 290	java/lang/StringBuilder:<init>	()V
    //   2758: ldc_w 459
    //   2761: invokevirtual 296	java/lang/StringBuilder:append	(Ljava/lang/String;)Ljava/lang/StringBuilder;
    //   2764: aload 99
    //   2766: ldc 232
    //   2768: invokevirtual 477	weibo4android/org/json/JSONObject:getLong	(Ljava/lang/String;)J
    //   2771: invokevirtual 480	java/lang/StringBuilder:append	(J)Ljava/lang/StringBuilder;
    //   2774: invokevirtual 304	java/lang/StringBuilder:toString	()Ljava/lang/String;
    //   2777: invokevirtual 47	java/io/PrintStream:println	(Ljava/lang/String;)V
    //   2780: getstatic 35	java/lang/System:out	Ljava/io/PrintStream;
    //   2783: new 289	java/lang/StringBuilder
    //   2786: dup
    //   2787: invokespecial 290	java/lang/StringBuilder:<init>	()V
    //   2790: ldc_w 461
    //   2793: invokevirtual 296	java/lang/StringBuilder:append	(Ljava/lang/String;)Ljava/lang/StringBuilder;
    //   2796: aload 99
    //   2798: ldc 179
    //   2800: invokevirtual 477	weibo4android/org/json/JSONObject:getLong	(Ljava/lang/String;)J
    //   2803: invokevirtual 480	java/lang/StringBuilder:append	(J)Ljava/lang/StringBuilder;
    //   2806: invokevirtual 304	java/lang/StringBuilder:toString	()Ljava/lang/String;
    //   2809: invokevirtual 47	java/io/PrintStream:println	(Ljava/lang/String;)V
    //   2812: getstatic 35	java/lang/System:out	Ljava/io/PrintStream;
    //   2815: new 289	java/lang/StringBuilder
    //   2818: dup
    //   2819: invokespecial 290	java/lang/StringBuilder:<init>	()V
    //   2822: ldc_w 463
    //   2825: invokevirtual 296	java/lang/StringBuilder:append	(Ljava/lang/String;)Ljava/lang/StringBuilder;
    //   2828: aload 99
    //   2830: ldc_w 465
    //   2833: invokevirtual 477	weibo4android/org/json/JSONObject:getLong	(Ljava/lang/String;)J
    //   2836: invokevirtual 480	java/lang/StringBuilder:append	(J)Ljava/lang/StringBuilder;
    //   2839: invokevirtual 304	java/lang/StringBuilder:toString	()Ljava/lang/String;
    //   2842: invokevirtual 47	java/io/PrintStream:println	(Ljava/lang/String;)V
    //   2845: getstatic 35	java/lang/System:out	Ljava/io/PrintStream;
    //   2848: new 289	java/lang/StringBuilder
    //   2851: dup
    //   2852: invokespecial 290	java/lang/StringBuilder:<init>	()V
    //   2855: ldc_w 467
    //   2858: invokevirtual 296	java/lang/StringBuilder:append	(Ljava/lang/String;)Ljava/lang/StringBuilder;
    //   2861: aload 99
    //   2863: ldc 237
    //   2865: invokevirtual 477	weibo4android/org/json/JSONObject:getLong	(Ljava/lang/String;)J
    //   2868: invokevirtual 480	java/lang/StringBuilder:append	(J)Ljava/lang/StringBuilder;
    //   2871: invokevirtual 304	java/lang/StringBuilder:toString	()Ljava/lang/String;
    //   2874: invokevirtual 47	java/io/PrintStream:println	(Ljava/lang/String;)V
    //   2877: getstatic 35	java/lang/System:out	Ljava/io/PrintStream;
    //   2880: new 289	java/lang/StringBuilder
    //   2883: dup
    //   2884: invokespecial 290	java/lang/StringBuilder:<init>	()V
    //   2887: ldc_w 469
    //   2890: invokevirtual 296	java/lang/StringBuilder:append	(Ljava/lang/String;)Ljava/lang/StringBuilder;
    //   2893: aload 99
    //   2895: ldc_w 471
    //   2898: invokevirtual 477	weibo4android/org/json/JSONObject:getLong	(Ljava/lang/String;)J
    //   2901: invokevirtual 480	java/lang/StringBuilder:append	(J)Ljava/lang/StringBuilder;
    //   2904: invokevirtual 304	java/lang/StringBuilder:toString	()Ljava/lang/String;
    //   2907: invokevirtual 47	java/io/PrintStream:println	(Ljava/lang/String;)V
    //   2910: getstatic 35	java/lang/System:out	Ljava/io/PrintStream;
    //   2913: ldc_w 482
    //   2916: invokevirtual 47	java/io/PrintStream:println	(Ljava/lang/String;)V
    //   2919: getstatic 35	java/lang/System:out	Ljava/io/PrintStream;
    //   2922: new 289	java/lang/StringBuilder
    //   2925: dup
    //   2926: invokespecial 290	java/lang/StringBuilder:<init>	()V
    //   2929: ldc_w 459
    //   2932: invokevirtual 296	java/lang/StringBuilder:append	(Ljava/lang/String;)Ljava/lang/StringBuilder;
    //   2935: aload 99
    //   2937: ldc 232
    //   2939: invokevirtual 300	weibo4android/org/json/JSONObject:getDouble	(Ljava/lang/String;)D
    //   2942: invokevirtual 303	java/lang/StringBuilder:append	(D)Ljava/lang/StringBuilder;
    //   2945: invokevirtual 304	java/lang/StringBuilder:toString	()Ljava/lang/String;
    //   2948: invokevirtual 47	java/io/PrintStream:println	(Ljava/lang/String;)V
    //   2951: getstatic 35	java/lang/System:out	Ljava/io/PrintStream;
    //   2954: new 289	java/lang/StringBuilder
    //   2957: dup
    //   2958: invokespecial 290	java/lang/StringBuilder:<init>	()V
    //   2961: ldc_w 461
    //   2964: invokevirtual 296	java/lang/StringBuilder:append	(Ljava/lang/String;)Ljava/lang/StringBuilder;
    //   2967: aload 99
    //   2969: ldc 179
    //   2971: invokevirtual 300	weibo4android/org/json/JSONObject:getDouble	(Ljava/lang/String;)D
    //   2974: invokevirtual 303	java/lang/StringBuilder:append	(D)Ljava/lang/StringBuilder;
    //   2977: invokevirtual 304	java/lang/StringBuilder:toString	()Ljava/lang/String;
    //   2980: invokevirtual 47	java/io/PrintStream:println	(Ljava/lang/String;)V
    //   2983: getstatic 35	java/lang/System:out	Ljava/io/PrintStream;
    //   2986: new 289	java/lang/StringBuilder
    //   2989: dup
    //   2990: invokespecial 290	java/lang/StringBuilder:<init>	()V
    //   2993: ldc_w 463
    //   2996: invokevirtual 296	java/lang/StringBuilder:append	(Ljava/lang/String;)Ljava/lang/StringBuilder;
    //   2999: aload 99
    //   3001: ldc_w 465
    //   3004: invokevirtual 300	weibo4android/org/json/JSONObject:getDouble	(Ljava/lang/String;)D
    //   3007: invokevirtual 303	java/lang/StringBuilder:append	(D)Ljava/lang/StringBuilder;
    //   3010: invokevirtual 304	java/lang/StringBuilder:toString	()Ljava/lang/String;
    //   3013: invokevirtual 47	java/io/PrintStream:println	(Ljava/lang/String;)V
    //   3016: getstatic 35	java/lang/System:out	Ljava/io/PrintStream;
    //   3019: new 289	java/lang/StringBuilder
    //   3022: dup
    //   3023: invokespecial 290	java/lang/StringBuilder:<init>	()V
    //   3026: ldc_w 467
    //   3029: invokevirtual 296	java/lang/StringBuilder:append	(Ljava/lang/String;)Ljava/lang/StringBuilder;
    //   3032: aload 99
    //   3034: ldc 237
    //   3036: invokevirtual 300	weibo4android/org/json/JSONObject:getDouble	(Ljava/lang/String;)D
    //   3039: invokevirtual 303	java/lang/StringBuilder:append	(D)Ljava/lang/StringBuilder;
    //   3042: invokevirtual 304	java/lang/StringBuilder:toString	()Ljava/lang/String;
    //   3045: invokevirtual 47	java/io/PrintStream:println	(Ljava/lang/String;)V
    //   3048: getstatic 35	java/lang/System:out	Ljava/io/PrintStream;
    //   3051: new 289	java/lang/StringBuilder
    //   3054: dup
    //   3055: invokespecial 290	java/lang/StringBuilder:<init>	()V
    //   3058: ldc_w 469
    //   3061: invokevirtual 296	java/lang/StringBuilder:append	(Ljava/lang/String;)Ljava/lang/StringBuilder;
    //   3064: aload 99
    //   3066: ldc_w 471
    //   3069: invokevirtual 300	weibo4android/org/json/JSONObject:getDouble	(Ljava/lang/String;)D
    //   3072: invokevirtual 303	java/lang/StringBuilder:append	(D)Ljava/lang/StringBuilder;
    //   3075: invokevirtual 304	java/lang/StringBuilder:toString	()Ljava/lang/String;
    //   3078: invokevirtual 47	java/io/PrintStream:println	(Ljava/lang/String;)V
    //   3081: aload 99
    //   3083: ldc_w 484
    //   3086: ldc2_w 180
    //   3089: invokevirtual 487	weibo4android/org/json/JSONObject:put	(Ljava/lang/String;J)Lweibo4android/org/json/JSONObject;
    //   3092: pop
    //   3093: getstatic 35	java/lang/System:out	Ljava/io/PrintStream;
    //   3096: aload 99
    //   3098: iconst_4
    //   3099: invokevirtual 54	weibo4android/org/json/JSONObject:toString	(I)Ljava/lang/String;
    //   3102: invokevirtual 47	java/io/PrintStream:println	(Ljava/lang/String;)V
    //   3105: new 73	weibo4android/org/json/JSONArray
    //   3108: dup
    //   3109: ldc_w 489
    //   3112: invokespecial 195	weibo4android/org/json/JSONArray:<init>	(Ljava/lang/String;)V
    //   3115: astore 101
    //   3117: getstatic 35	java/lang/System:out	Ljava/io/PrintStream;
    //   3120: aload 101
    //   3122: iconst_4
    //   3123: invokevirtual 74	weibo4android/org/json/JSONArray:toString	(I)Ljava/lang/String;
    //   3126: invokevirtual 47	java/io/PrintStream:println	(Ljava/lang/String;)V
    //   3129: getstatic 35	java/lang/System:out	Ljava/io/PrintStream;
    //   3132: ldc_w 491
    //   3135: invokevirtual 47	java/io/PrintStream:println	(Ljava/lang/String;)V
    //   3138: aload 99
    //   3140: invokevirtual 494	weibo4android/org/json/JSONObject:keys	()Ljava/util/Iterator;
    //   3143: astore 102
    //   3145: aload 102
    //   3147: invokeinterface 500 1 0
    //   3152: ifeq +67 -> 3219
    //   3155: aload 102
    //   3157: invokeinterface 504 1 0
    //   3162: checkcast 199	java/lang/String
    //   3165: astore 157
    //   3167: getstatic 35	java/lang/System:out	Ljava/io/PrintStream;
    //   3170: new 289	java/lang/StringBuilder
    //   3173: dup
    //   3174: invokespecial 290	java/lang/StringBuilder:<init>	()V
    //   3177: aload 157
    //   3179: invokevirtual 296	java/lang/StringBuilder:append	(Ljava/lang/String;)Ljava/lang/StringBuilder;
    //   3182: ldc_w 506
    //   3185: invokevirtual 296	java/lang/StringBuilder:append	(Ljava/lang/String;)Ljava/lang/StringBuilder;
    //   3188: aload 99
    //   3190: aload 157
    //   3192: invokevirtual 321	weibo4android/org/json/JSONObject:getString	(Ljava/lang/String;)Ljava/lang/String;
    //   3195: invokevirtual 296	java/lang/StringBuilder:append	(Ljava/lang/String;)Ljava/lang/StringBuilder;
    //   3198: invokevirtual 304	java/lang/StringBuilder:toString	()Ljava/lang/String;
    //   3201: invokevirtual 47	java/io/PrintStream:println	(Ljava/lang/String;)V
    //   3204: goto -59 -> 3145
    //   3207: astore_2
    //   3208: getstatic 35	java/lang/System:out	Ljava/io/PrintStream;
    //   3211: aload_2
    //   3212: invokevirtual 507	java/lang/Exception:toString	()Ljava/lang/String;
    //   3215: invokevirtual 47	java/io/PrintStream:println	(Ljava/lang/String;)V
    //   3218: return
    //   3219: getstatic 35	java/lang/System:out	Ljava/io/PrintStream;
    //   3222: ldc_w 509
    //   3225: invokevirtual 47	java/io/PrintStream:println	(Ljava/lang/String;)V
    //   3228: new 37	weibo4android/org/json/JSONObject
    //   3231: dup
    //   3232: invokespecial 227	weibo4android/org/json/JSONObject:<init>	()V
    //   3235: astore 103
    //   3237: aload 103
    //   3239: ldc_w 511
    //   3242: ldc_w 513
    //   3245: invokevirtual 516	weibo4android/org/json/JSONObject:accumulate	(Ljava/lang/String;Ljava/lang/Object;)Lweibo4android/org/json/JSONObject;
    //   3248: pop
    //   3249: aload 103
    //   3251: ldc_w 511
    //   3254: ldc_w 518
    //   3257: invokevirtual 516	weibo4android/org/json/JSONObject:accumulate	(Ljava/lang/String;Ljava/lang/Object;)Lweibo4android/org/json/JSONObject;
    //   3260: pop
    //   3261: aload 103
    //   3263: ldc_w 511
    //   3266: ldc_w 520
    //   3269: invokevirtual 516	weibo4android/org/json/JSONObject:accumulate	(Ljava/lang/String;Ljava/lang/Object;)Lweibo4android/org/json/JSONObject;
    //   3272: pop
    //   3273: aload 103
    //   3275: ldc_w 511
    //   3278: invokevirtual 264	weibo4android/org/json/JSONObject:getJSONArray	(Ljava/lang/String;)Lweibo4android/org/json/JSONArray;
    //   3281: iconst_5
    //   3282: ldc_w 522
    //   3285: invokevirtual 525	weibo4android/org/json/JSONArray:put	(ILjava/lang/Object;)Lweibo4android/org/json/JSONArray;
    //   3288: pop
    //   3289: getstatic 35	java/lang/System:out	Ljava/io/PrintStream;
    //   3292: aload 103
    //   3294: iconst_4
    //   3295: invokevirtual 54	weibo4android/org/json/JSONObject:toString	(I)Ljava/lang/String;
    //   3298: invokevirtual 47	java/io/PrintStream:println	(Ljava/lang/String;)V
    //   3301: getstatic 35	java/lang/System:out	Ljava/io/PrintStream;
    //   3304: ldc_w 527
    //   3307: invokevirtual 47	java/io/PrintStream:println	(Ljava/lang/String;)V
    //   3310: getstatic 35	java/lang/System:out	Ljava/io/PrintStream;
    //   3313: aload 103
    //   3315: new 529	java/io/StringWriter
    //   3318: dup
    //   3319: invokespecial 530	java/io/StringWriter:<init>	()V
    //   3322: invokevirtual 534	weibo4android/org/json/JSONObject:write	(Ljava/io/Writer;)Ljava/io/Writer;
    //   3325: invokevirtual 453	java/io/PrintStream:println	(Ljava/lang/Object;)V
    //   3328: ldc_w 536
    //   3331: invokestatic 29	weibo4android/org/json/XML:toJSONObject	(Ljava/lang/String;)Lweibo4android/org/json/JSONObject;
    //   3334: astore 108
    //   3336: getstatic 35	java/lang/System:out	Ljava/io/PrintStream;
    //   3339: aload 108
    //   3341: iconst_4
    //   3342: invokevirtual 54	weibo4android/org/json/JSONObject:toString	(I)Ljava/lang/String;
    //   3345: invokevirtual 47	java/io/PrintStream:println	(Ljava/lang/String;)V
    //   3348: getstatic 35	java/lang/System:out	Ljava/io/PrintStream;
    //   3351: aload 108
    //   3353: invokestatic 57	weibo4android/org/json/XML:toString	(Ljava/lang/Object;)Ljava/lang/String;
    //   3356: invokevirtual 47	java/io/PrintStream:println	(Ljava/lang/String;)V
    //   3359: ldc_w 538
    //   3362: invokestatic 29	weibo4android/org/json/XML:toJSONObject	(Ljava/lang/String;)Lweibo4android/org/json/JSONObject;
    //   3365: astore 109
    //   3367: getstatic 35	java/lang/System:out	Ljava/io/PrintStream;
    //   3370: aload 109
    //   3372: iconst_4
    //   3373: invokevirtual 54	weibo4android/org/json/JSONObject:toString	(I)Ljava/lang/String;
    //   3376: invokevirtual 47	java/io/PrintStream:println	(Ljava/lang/String;)V
    //   3379: getstatic 35	java/lang/System:out	Ljava/io/PrintStream;
    //   3382: aload 109
    //   3384: invokestatic 57	weibo4android/org/json/XML:toString	(Ljava/lang/Object;)Ljava/lang/String;
    //   3387: invokevirtual 47	java/io/PrintStream:println	(Ljava/lang/String;)V
    //   3390: ldc_w 538
    //   3393: invokestatic 71	weibo4android/org/json/JSONML:toJSONArray	(Ljava/lang/String;)Lweibo4android/org/json/JSONArray;
    //   3396: astore 110
    //   3398: getstatic 35	java/lang/System:out	Ljava/io/PrintStream;
    //   3401: aload 110
    //   3403: iconst_4
    //   3404: invokevirtual 74	weibo4android/org/json/JSONArray:toString	(I)Ljava/lang/String;
    //   3407: invokevirtual 47	java/io/PrintStream:println	(Ljava/lang/String;)V
    //   3410: getstatic 35	java/lang/System:out	Ljava/io/PrintStream;
    //   3413: aload 110
    //   3415: invokestatic 77	weibo4android/org/json/JSONML:toString	(Lweibo4android/org/json/JSONArray;)Ljava/lang/String;
    //   3418: invokevirtual 47	java/io/PrintStream:println	(Ljava/lang/String;)V
    //   3421: new 37	weibo4android/org/json/JSONObject
    //   3424: dup
    //   3425: aconst_null
    //   3426: invokespecial 541	weibo4android/org/json/JSONObject:<init>	(Ljava/util/Map;)V
    //   3429: astore 111
    //   3431: new 73	weibo4android/org/json/JSONArray
    //   3434: dup
    //   3435: aconst_null
    //   3436: invokespecial 544	weibo4android/org/json/JSONArray:<init>	(Ljava/util/Collection;)V
    //   3439: astore 112
    //   3441: aload 111
    //   3443: ldc_w 511
    //   3446: ldc_w 546
    //   3449: invokevirtual 548	weibo4android/org/json/JSONObject:append	(Ljava/lang/String;Ljava/lang/Object;)Lweibo4android/org/json/JSONObject;
    //   3452: pop
    //   3453: aload 111
    //   3455: ldc_w 511
    //   3458: ldc_w 522
    //   3461: invokevirtual 548	weibo4android/org/json/JSONObject:append	(Ljava/lang/String;Ljava/lang/Object;)Lweibo4android/org/json/JSONObject;
    //   3464: pop
    //   3465: aload 111
    //   3467: ldc_w 550
    //   3470: ldc_w 513
    //   3473: invokevirtual 516	weibo4android/org/json/JSONObject:accumulate	(Ljava/lang/String;Ljava/lang/Object;)Lweibo4android/org/json/JSONObject;
    //   3476: pop
    //   3477: aload 111
    //   3479: ldc_w 550
    //   3482: ldc_w 518
    //   3485: invokevirtual 516	weibo4android/org/json/JSONObject:accumulate	(Ljava/lang/String;Ljava/lang/Object;)Lweibo4android/org/json/JSONObject;
    //   3488: pop
    //   3489: aload 111
    //   3491: ldc_w 550
    //   3494: ldc_w 520
    //   3497: invokevirtual 516	weibo4android/org/json/JSONObject:accumulate	(Ljava/lang/String;Ljava/lang/Object;)Lweibo4android/org/json/JSONObject;
    //   3500: pop
    //   3501: aload 111
    //   3503: ldc_w 552
    //   3506: aload 111
    //   3508: ldc_w 550
    //   3511: invokevirtual 556	weibo4android/org/json/JSONObject:get	(Ljava/lang/String;)Ljava/lang/Object;
    //   3514: invokevirtual 516	weibo4android/org/json/JSONObject:accumulate	(Ljava/lang/String;Ljava/lang/Object;)Lweibo4android/org/json/JSONObject;
    //   3517: pop
    //   3518: aload 111
    //   3520: ldc_w 558
    //   3523: aconst_null
    //   3524: invokevirtual 561	weibo4android/org/json/JSONObject:put	(Ljava/lang/String;Ljava/util/Map;)Lweibo4android/org/json/JSONObject;
    //   3527: pop
    //   3528: aload 111
    //   3530: ldc_w 563
    //   3533: aconst_null
    //   3534: invokevirtual 566	weibo4android/org/json/JSONObject:put	(Ljava/lang/String;Ljava/util/Collection;)Lweibo4android/org/json/JSONObject;
    //   3537: pop
    //   3538: aload 111
    //   3540: ldc_w 567
    //   3543: aload 112
    //   3545: invokevirtual 214	weibo4android/org/json/JSONObject:put	(Ljava/lang/String;Ljava/lang/Object;)Lweibo4android/org/json/JSONObject;
    //   3548: pop
    //   3549: aload 112
    //   3551: aconst_null
    //   3552: invokevirtual 570	weibo4android/org/json/JSONArray:put	(Ljava/util/Map;)Lweibo4android/org/json/JSONArray;
    //   3555: pop
    //   3556: aload 112
    //   3558: aconst_null
    //   3559: invokevirtual 573	weibo4android/org/json/JSONArray:put	(Ljava/util/Collection;)Lweibo4android/org/json/JSONArray;
    //   3562: pop
    //   3563: getstatic 35	java/lang/System:out	Ljava/io/PrintStream;
    //   3566: aload 111
    //   3568: iconst_4
    //   3569: invokevirtual 54	weibo4android/org/json/JSONObject:toString	(I)Ljava/lang/String;
    //   3572: invokevirtual 47	java/io/PrintStream:println	(Ljava/lang/String;)V
    //   3575: new 37	weibo4android/org/json/JSONObject
    //   3578: dup
    //   3579: ldc_w 575
    //   3582: invokespecial 51	weibo4android/org/json/JSONObject:<init>	(Ljava/lang/String;)V
    //   3585: astore 124
    //   3587: getstatic 35	java/lang/System:out	Ljava/io/PrintStream;
    //   3590: aload 124
    //   3592: iconst_4
    //   3593: invokevirtual 54	weibo4android/org/json/JSONObject:toString	(I)Ljava/lang/String;
    //   3596: invokevirtual 47	java/io/PrintStream:println	(Ljava/lang/String;)V
    //   3599: new 73	weibo4android/org/json/JSONArray
    //   3602: dup
    //   3603: ldc_w 577
    //   3606: invokespecial 195	weibo4android/org/json/JSONArray:<init>	(Ljava/lang/String;)V
    //   3609: astore 125
    //   3611: getstatic 35	java/lang/System:out	Ljava/io/PrintStream;
    //   3614: aload 125
    //   3616: invokevirtual 197	weibo4android/org/json/JSONArray:toString	()Ljava/lang/String;
    //   3619: invokevirtual 47	java/io/PrintStream:println	(Ljava/lang/String;)V
    //   3622: ldc_w 579
    //   3625: invokestatic 29	weibo4android/org/json/XML:toJSONObject	(Ljava/lang/String;)Lweibo4android/org/json/JSONObject;
    //   3628: astore 126
    //   3630: getstatic 35	java/lang/System:out	Ljava/io/PrintStream;
    //   3633: aload 126
    //   3635: iconst_2
    //   3636: invokevirtual 54	weibo4android/org/json/JSONObject:toString	(I)Ljava/lang/String;
    //   3639: invokevirtual 47	java/io/PrintStream:println	(Ljava/lang/String;)V
    //   3642: getstatic 35	java/lang/System:out	Ljava/io/PrintStream;
    //   3645: aload 126
    //   3647: invokestatic 57	weibo4android/org/json/XML:toString	(Ljava/lang/Object;)Ljava/lang/String;
    //   3650: invokevirtual 47	java/io/PrintStream:println	(Ljava/lang/String;)V
    //   3653: getstatic 35	java/lang/System:out	Ljava/io/PrintStream;
    //   3656: ldc 218
    //   3658: invokevirtual 47	java/io/PrintStream:println	(Ljava/lang/String;)V
    //   3661: ldc_w 579
    //   3664: invokestatic 71	weibo4android/org/json/JSONML:toJSONArray	(Ljava/lang/String;)Lweibo4android/org/json/JSONArray;
    //   3667: astore 127
    //   3669: getstatic 35	java/lang/System:out	Ljava/io/PrintStream;
    //   3672: aload 127
    //   3674: iconst_4
    //   3675: invokevirtual 74	weibo4android/org/json/JSONArray:toString	(I)Ljava/lang/String;
    //   3678: invokevirtual 47	java/io/PrintStream:println	(Ljava/lang/String;)V
    //   3681: getstatic 35	java/lang/System:out	Ljava/io/PrintStream;
    //   3684: aload 127
    //   3686: invokestatic 77	weibo4android/org/json/JSONML:toString	(Lweibo4android/org/json/JSONArray;)Ljava/lang/String;
    //   3689: invokevirtual 47	java/io/PrintStream:println	(Ljava/lang/String;)V
    //   3692: getstatic 35	java/lang/System:out	Ljava/io/PrintStream;
    //   3695: ldc 218
    //   3697: invokevirtual 47	java/io/PrintStream:println	(Ljava/lang/String;)V
    //   3700: getstatic 35	java/lang/System:out	Ljava/io/PrintStream;
    //   3703: ldc_w 581
    //   3706: invokevirtual 47	java/io/PrintStream:println	(Ljava/lang/String;)V
    //   3709: getstatic 35	java/lang/System:out	Ljava/io/PrintStream;
    //   3712: ldc_w 583
    //   3715: invokevirtual 586	java/io/PrintStream:print	(Ljava/lang/String;)V
    //   3718: new 73	weibo4android/org/json/JSONArray
    //   3721: dup
    //   3722: invokespecial 230	weibo4android/org/json/JSONArray:<init>	()V
    //   3725: astore 128
    //   3727: aload 128
    //   3729: ldc2_w 587
    //   3732: invokevirtual 272	weibo4android/org/json/JSONArray:put	(D)Lweibo4android/org/json/JSONArray;
    //   3735: pop
    //   3736: aload 128
    //   3738: ldc2_w 589
    //   3741: invokevirtual 272	weibo4android/org/json/JSONArray:put	(D)Lweibo4android/org/json/JSONArray;
    //   3744: pop
    //   3745: getstatic 35	java/lang/System:out	Ljava/io/PrintStream;
    //   3748: aload 128
    //   3750: invokevirtual 197	weibo4android/org/json/JSONArray:toString	()Ljava/lang/String;
    //   3753: invokevirtual 47	java/io/PrintStream:println	(Ljava/lang/String;)V
    //   3756: getstatic 35	java/lang/System:out	Ljava/io/PrintStream;
    //   3759: ldc_w 583
    //   3762: invokevirtual 586	java/io/PrintStream:print	(Ljava/lang/String;)V
    //   3765: getstatic 35	java/lang/System:out	Ljava/io/PrintStream;
    //   3768: aload 126
    //   3770: ldc_w 511
    //   3773: invokevirtual 300	weibo4android/org/json/JSONObject:getDouble	(Ljava/lang/String;)D
    //   3776: invokevirtual 593	java/io/PrintStream:println	(D)V
    //   3779: getstatic 35	java/lang/System:out	Ljava/io/PrintStream;
    //   3782: ldc_w 583
    //   3785: invokevirtual 586	java/io/PrintStream:print	(Ljava/lang/String;)V
    //   3788: getstatic 35	java/lang/System:out	Ljava/io/PrintStream;
    //   3791: aload 126
    //   3793: ldc_w 595
    //   3796: invokevirtual 300	weibo4android/org/json/JSONObject:getDouble	(Ljava/lang/String;)D
    //   3799: invokevirtual 593	java/io/PrintStream:println	(D)V
    //   3802: getstatic 35	java/lang/System:out	Ljava/io/PrintStream;
    //   3805: ldc_w 583
    //   3808: invokevirtual 586	java/io/PrintStream:print	(Ljava/lang/String;)V
    //   3811: getstatic 35	java/lang/System:out	Ljava/io/PrintStream;
    //   3814: aload 126
    //   3816: aconst_null
    //   3817: ldc_w 595
    //   3820: invokevirtual 214	weibo4android/org/json/JSONObject:put	(Ljava/lang/String;Ljava/lang/Object;)Lweibo4android/org/json/JSONObject;
    //   3823: invokevirtual 453	java/io/PrintStream:println	(Ljava/lang/Object;)V
    //   3826: getstatic 35	java/lang/System:out	Ljava/io/PrintStream;
    //   3829: ldc_w 583
    //   3832: invokevirtual 586	java/io/PrintStream:print	(Ljava/lang/String;)V
    //   3835: getstatic 35	java/lang/System:out	Ljava/io/PrintStream;
    //   3838: aload 128
    //   3840: iconst_0
    //   3841: invokevirtual 598	weibo4android/org/json/JSONArray:getDouble	(I)D
    //   3844: invokevirtual 593	java/io/PrintStream:println	(D)V
    //   3847: getstatic 35	java/lang/System:out	Ljava/io/PrintStream;
    //   3850: ldc_w 583
    //   3853: invokevirtual 586	java/io/PrintStream:print	(Ljava/lang/String;)V
    //   3856: getstatic 35	java/lang/System:out	Ljava/io/PrintStream;
    //   3859: aload 128
    //   3861: iconst_m1
    //   3862: invokevirtual 601	weibo4android/org/json/JSONArray:get	(I)Ljava/lang/Object;
    //   3865: invokevirtual 453	java/io/PrintStream:println	(Ljava/lang/Object;)V
    //   3868: getstatic 35	java/lang/System:out	Ljava/io/PrintStream;
    //   3871: ldc_w 583
    //   3874: invokevirtual 586	java/io/PrintStream:print	(Ljava/lang/String;)V
    //   3877: getstatic 35	java/lang/System:out	Ljava/io/PrintStream;
    //   3880: aload 128
    //   3882: ldc2_w 589
    //   3885: invokevirtual 272	weibo4android/org/json/JSONArray:put	(D)Lweibo4android/org/json/JSONArray;
    //   3888: invokevirtual 453	java/io/PrintStream:println	(Ljava/lang/Object;)V
    //   3891: getstatic 35	java/lang/System:out	Ljava/io/PrintStream;
    //   3894: ldc_w 583
    //   3897: invokevirtual 586	java/io/PrintStream:print	(Ljava/lang/String;)V
    //   3900: ldc_w 603
    //   3903: invokestatic 29	weibo4android/org/json/XML:toJSONObject	(Ljava/lang/String;)Lweibo4android/org/json/JSONObject;
    //   3906: astore 154
    //   3908: aload 154
    //   3910: astore 137
    //   3912: getstatic 35	java/lang/System:out	Ljava/io/PrintStream;
    //   3915: ldc_w 583
    //   3918: invokevirtual 586	java/io/PrintStream:print	(Ljava/lang/String;)V
    //   3921: ldc_w 605
    //   3924: invokestatic 29	weibo4android/org/json/XML:toJSONObject	(Ljava/lang/String;)Lweibo4android/org/json/JSONObject;
    //   3927: astore 153
    //   3929: aload 153
    //   3931: astore 137
    //   3933: getstatic 35	java/lang/System:out	Ljava/io/PrintStream;
    //   3936: ldc_w 583
    //   3939: invokevirtual 586	java/io/PrintStream:print	(Ljava/lang/String;)V
    //   3942: ldc_w 607
    //   3945: invokestatic 29	weibo4android/org/json/XML:toJSONObject	(Ljava/lang/String;)Lweibo4android/org/json/JSONObject;
    //   3948: astore 152
    //   3950: aload 152
    //   3952: astore 137
    //   3954: getstatic 35	java/lang/System:out	Ljava/io/PrintStream;
    //   3957: ldc_w 583
    //   3960: invokevirtual 586	java/io/PrintStream:print	(Ljava/lang/String;)V
    //   3963: new 73	weibo4android/org/json/JSONArray
    //   3966: dup
    //   3967: new 4	java/lang/Object
    //   3970: dup
    //   3971: invokespecial 8	java/lang/Object:<init>	()V
    //   3974: invokespecial 196	weibo4android/org/json/JSONArray:<init>	(Ljava/lang/Object;)V
    //   3977: astore 140
    //   3979: getstatic 35	java/lang/System:out	Ljava/io/PrintStream;
    //   3982: aload 140
    //   3984: invokevirtual 197	weibo4android/org/json/JSONArray:toString	()Ljava/lang/String;
    //   3987: invokevirtual 47	java/io/PrintStream:println	(Ljava/lang/String;)V
    //   3990: getstatic 35	java/lang/System:out	Ljava/io/PrintStream;
    //   3993: ldc_w 583
    //   3996: invokevirtual 586	java/io/PrintStream:print	(Ljava/lang/String;)V
    //   3999: new 73	weibo4android/org/json/JSONArray
    //   4002: dup
    //   4003: ldc_w 609
    //   4006: invokespecial 195	weibo4android/org/json/JSONArray:<init>	(Ljava/lang/String;)V
    //   4009: astore 142
    //   4011: getstatic 35	java/lang/System:out	Ljava/io/PrintStream;
    //   4014: aload 142
    //   4016: invokevirtual 197	weibo4android/org/json/JSONArray:toString	()Ljava/lang/String;
    //   4019: invokevirtual 47	java/io/PrintStream:println	(Ljava/lang/String;)V
    //   4022: getstatic 35	java/lang/System:out	Ljava/io/PrintStream;
    //   4025: ldc_w 583
    //   4028: invokevirtual 586	java/io/PrintStream:print	(Ljava/lang/String;)V
    //   4031: ldc_w 611
    //   4034: invokestatic 71	weibo4android/org/json/JSONML:toJSONArray	(Ljava/lang/String;)Lweibo4android/org/json/JSONArray;
    //   4037: astore 151
    //   4039: getstatic 35	java/lang/System:out	Ljava/io/PrintStream;
    //   4042: aload 151
    //   4044: iconst_4
    //   4045: invokevirtual 74	weibo4android/org/json/JSONArray:toString	(I)Ljava/lang/String;
    //   4048: invokevirtual 47	java/io/PrintStream:println	(Ljava/lang/String;)V
    //   4051: getstatic 35	java/lang/System:out	Ljava/io/PrintStream;
    //   4054: ldc_w 583
    //   4057: invokevirtual 586	java/io/PrintStream:print	(Ljava/lang/String;)V
    //   4060: ldc_w 613
    //   4063: invokestatic 71	weibo4android/org/json/JSONML:toJSONArray	(Ljava/lang/String;)Lweibo4android/org/json/JSONArray;
    //   4066: astore 150
    //   4068: getstatic 35	java/lang/System:out	Ljava/io/PrintStream;
    //   4071: aload 150
    //   4073: iconst_4
    //   4074: invokevirtual 74	weibo4android/org/json/JSONArray:toString	(I)Ljava/lang/String;
    //   4077: invokevirtual 47	java/io/PrintStream:println	(Ljava/lang/String;)V
    //   4080: getstatic 35	java/lang/System:out	Ljava/io/PrintStream;
    //   4083: ldc_w 583
    //   4086: invokevirtual 586	java/io/PrintStream:print	(Ljava/lang/String;)V
    //   4089: new 37	weibo4android/org/json/JSONObject
    //   4092: dup
    //   4093: ldc_w 615
    //   4096: invokespecial 51	weibo4android/org/json/JSONObject:<init>	(Ljava/lang/String;)V
    //   4099: astore 146
    //   4101: getstatic 35	java/lang/System:out	Ljava/io/PrintStream;
    //   4104: aload 146
    //   4106: iconst_4
    //   4107: invokevirtual 54	weibo4android/org/json/JSONObject:toString	(I)Ljava/lang/String;
    //   4110: invokevirtual 47	java/io/PrintStream:println	(Ljava/lang/String;)V
    //   4113: getstatic 35	java/lang/System:out	Ljava/io/PrintStream;
    //   4116: ldc_w 583
    //   4119: invokevirtual 586	java/io/PrintStream:print	(Ljava/lang/String;)V
    //   4122: new 88	weibo4android/org/json/JSONStringer
    //   4125: dup
    //   4126: invokespecial 89	weibo4android/org/json/JSONStringer:<init>	()V
    //   4129: invokevirtual 93	weibo4android/org/json/JSONStringer:object	()Lweibo4android/org/json/JSONWriter;
    //   4132: ldc_w 617
    //   4135: invokevirtual 101	weibo4android/org/json/JSONWriter:key	(Ljava/lang/String;)Lweibo4android/org/json/JSONWriter;
    //   4138: ldc 103
    //   4140: invokevirtual 107	weibo4android/org/json/JSONWriter:value	(Ljava/lang/Object;)Lweibo4android/org/json/JSONWriter;
    //   4143: ldc_w 617
    //   4146: invokevirtual 101	weibo4android/org/json/JSONWriter:key	(Ljava/lang/String;)Lweibo4android/org/json/JSONWriter;
    //   4149: ldc 111
    //   4151: invokevirtual 107	weibo4android/org/json/JSONWriter:value	(Ljava/lang/Object;)Lweibo4android/org/json/JSONWriter;
    //   4154: invokevirtual 128	weibo4android/org/json/JSONWriter:endObject	()Lweibo4android/org/json/JSONWriter;
    //   4157: invokevirtual 138	java/lang/Object:toString	()Ljava/lang/String;
    //   4160: pop
    //   4161: getstatic 35	java/lang/System:out	Ljava/io/PrintStream;
    //   4164: aload 146
    //   4166: iconst_4
    //   4167: invokevirtual 54	weibo4android/org/json/JSONObject:toString	(I)Ljava/lang/String;
    //   4170: invokevirtual 47	java/io/PrintStream:println	(Ljava/lang/String;)V
    //   4173: return
    //   4174: astore 148
    //   4176: getstatic 35	java/lang/System:out	Ljava/io/PrintStream;
    //   4179: aload 148
    //   4181: invokevirtual 453	java/io/PrintStream:println	(Ljava/lang/Object;)V
    //   4184: return
    //   4185: getstatic 35	java/lang/System:out	Ljava/io/PrintStream;
    //   4188: aload 129
    //   4190: invokevirtual 453	java/io/PrintStream:println	(Ljava/lang/Object;)V
    //   4193: goto -437 -> 3756
    //   4196: astore 130
    //   4198: getstatic 35	java/lang/System:out	Ljava/io/PrintStream;
    //   4201: aload 130
    //   4203: invokevirtual 453	java/io/PrintStream:println	(Ljava/lang/Object;)V
    //   4206: goto -427 -> 3779
    //   4209: astore 131
    //   4211: getstatic 35	java/lang/System:out	Ljava/io/PrintStream;
    //   4214: aload 131
    //   4216: invokevirtual 453	java/io/PrintStream:println	(Ljava/lang/Object;)V
    //   4219: goto -417 -> 3802
    //   4222: astore 132
    //   4224: getstatic 35	java/lang/System:out	Ljava/io/PrintStream;
    //   4227: aload 132
    //   4229: invokevirtual 453	java/io/PrintStream:println	(Ljava/lang/Object;)V
    //   4232: goto -406 -> 3826
    //   4235: astore 133
    //   4237: getstatic 35	java/lang/System:out	Ljava/io/PrintStream;
    //   4240: aload 133
    //   4242: invokevirtual 453	java/io/PrintStream:println	(Ljava/lang/Object;)V
    //   4245: goto -398 -> 3847
    //   4248: astore 134
    //   4250: getstatic 35	java/lang/System:out	Ljava/io/PrintStream;
    //   4253: aload 134
    //   4255: invokevirtual 453	java/io/PrintStream:println	(Ljava/lang/Object;)V
    //   4258: goto -390 -> 3868
    //   4261: astore 135
    //   4263: getstatic 35	java/lang/System:out	Ljava/io/PrintStream;
    //   4266: aload 135
    //   4268: invokevirtual 453	java/io/PrintStream:println	(Ljava/lang/Object;)V
    //   4271: goto -380 -> 3891
    //   4274: astore 136
    //   4276: getstatic 35	java/lang/System:out	Ljava/io/PrintStream;
    //   4279: aload 136
    //   4281: invokevirtual 453	java/io/PrintStream:println	(Ljava/lang/Object;)V
    //   4284: aload 126
    //   4286: astore 137
    //   4288: goto -376 -> 3912
    //   4291: astore 138
    //   4293: getstatic 35	java/lang/System:out	Ljava/io/PrintStream;
    //   4296: aload 138
    //   4298: invokevirtual 453	java/io/PrintStream:println	(Ljava/lang/Object;)V
    //   4301: goto -368 -> 3933
    //   4304: astore 139
    //   4306: getstatic 35	java/lang/System:out	Ljava/io/PrintStream;
    //   4309: aload 139
    //   4311: invokevirtual 453	java/io/PrintStream:println	(Ljava/lang/Object;)V
    //   4314: goto -360 -> 3954
    //   4317: astore 141
    //   4319: getstatic 35	java/lang/System:out	Ljava/io/PrintStream;
    //   4322: aload 141
    //   4324: invokevirtual 453	java/io/PrintStream:println	(Ljava/lang/Object;)V
    //   4327: goto -337 -> 3990
    //   4330: astore 143
    //   4332: getstatic 35	java/lang/System:out	Ljava/io/PrintStream;
    //   4335: aload 143
    //   4337: invokevirtual 453	java/io/PrintStream:println	(Ljava/lang/Object;)V
    //   4340: goto -318 -> 4022
    //   4343: astore 144
    //   4345: getstatic 35	java/lang/System:out	Ljava/io/PrintStream;
    //   4348: aload 144
    //   4350: invokevirtual 453	java/io/PrintStream:println	(Ljava/lang/Object;)V
    //   4353: goto -302 -> 4051
    //   4356: astore 145
    //   4358: getstatic 35	java/lang/System:out	Ljava/io/PrintStream;
    //   4361: aload 145
    //   4363: invokevirtual 453	java/io/PrintStream:println	(Ljava/lang/Object;)V
    //   4366: goto -286 -> 4080
    //   4369: getstatic 35	java/lang/System:out	Ljava/io/PrintStream;
    //   4372: aload 147
    //   4374: invokevirtual 453	java/io/PrintStream:println	(Ljava/lang/Object;)V
    //   4377: goto -264 -> 4113
    //   4380: astore 147
    //   4382: goto -13 -> 4369
    //   4385: astore 129
    //   4387: goto -202 -> 4185
    //   4390: astore 129
    //   4392: aload 125
    //   4394: astore 128
    //   4396: goto -211 -> 4185
    //   4399: astore 147
    //   4401: aload 137
    //   4403: astore 146
    //   4405: goto -36 -> 4369
    //
    // Exception table:
    //   from	to	target	type
    //   14	2448	3207	java/lang/Exception
    //   2448	3145	3207	java/lang/Exception
    //   3145	3204	3207	java/lang/Exception
    //   3219	3718	3207	java/lang/Exception
    //   3756	3765	3207	java/lang/Exception
    //   3779	3788	3207	java/lang/Exception
    //   3802	3811	3207	java/lang/Exception
    //   3826	3835	3207	java/lang/Exception
    //   3847	3856	3207	java/lang/Exception
    //   3868	3877	3207	java/lang/Exception
    //   3891	3900	3207	java/lang/Exception
    //   3912	3921	3207	java/lang/Exception
    //   3933	3942	3207	java/lang/Exception
    //   3954	3963	3207	java/lang/Exception
    //   3990	3999	3207	java/lang/Exception
    //   4022	4031	3207	java/lang/Exception
    //   4051	4060	3207	java/lang/Exception
    //   4080	4089	3207	java/lang/Exception
    //   4113	4122	3207	java/lang/Exception
    //   4176	4184	3207	java/lang/Exception
    //   4185	4193	3207	java/lang/Exception
    //   4198	4206	3207	java/lang/Exception
    //   4211	4219	3207	java/lang/Exception
    //   4224	4232	3207	java/lang/Exception
    //   4237	4245	3207	java/lang/Exception
    //   4250	4258	3207	java/lang/Exception
    //   4263	4271	3207	java/lang/Exception
    //   4276	4284	3207	java/lang/Exception
    //   4293	4301	3207	java/lang/Exception
    //   4306	4314	3207	java/lang/Exception
    //   4319	4327	3207	java/lang/Exception
    //   4332	4340	3207	java/lang/Exception
    //   4345	4353	3207	java/lang/Exception
    //   4358	4366	3207	java/lang/Exception
    //   4369	4377	3207	java/lang/Exception
    //   4122	4173	4174	java/lang/Exception
    //   3765	3779	4196	java/lang/Exception
    //   3788	3802	4209	java/lang/Exception
    //   3811	3826	4222	java/lang/Exception
    //   3835	3847	4235	java/lang/Exception
    //   3856	3868	4248	java/lang/Exception
    //   3877	3891	4261	java/lang/Exception
    //   3900	3908	4274	java/lang/Exception
    //   3921	3929	4291	java/lang/Exception
    //   3942	3950	4304	java/lang/Exception
    //   3963	3990	4317	java/lang/Exception
    //   3999	4022	4330	java/lang/Exception
    //   4031	4051	4343	java/lang/Exception
    //   4060	4080	4356	java/lang/Exception
    //   4101	4113	4380	java/lang/Exception
    //   3727	3756	4385	java/lang/Exception
    //   3718	3727	4390	java/lang/Exception
    //   4089	4101	4399	java/lang/Exception
  }
}

/* Location:           /Users/zhangxun-xy/Downloads/qingting2/classes_dex2jar.jar
 * Qualified Name:     weibo4android.org.json.Test
 * JD-Core Version:    0.6.2
 */